Workbook

Sheet Grammar
A1: Reference: https://cvc.cervantes.es/ensenanza/biblioteca_ele/plan_curricular/niveles/02_gramatica_inventario_a1-a2.htm
A2: To check the glossary of the terms below: https://cvc.cervantes.es/ensenanza/biblioteca_ele/plan_curricular/niveles/02_gramatica_glosario.htm
A3: Section | B3: Subsection / Item | C3: Topic | D3: Example / Notes | E3: block 1 | F3: Block 2 | G3: block 3
A4: El sustantivo | B4: 1.1.1. Nombres propios | C4: Antropónimos – nombres de pila sin artículo | D4: María, Antonio | E4: =IFERROR(__xludf.DUMMYFUNCTION("IF( C4="""","""", N( ISNUMBER( MATCH( TRIM(SUBSTITUTE(SUBSTITUTE(SUBSTITUTE(SUBSTITUTE(SUBSTITUTE(TO_TEXT(C4),CHAR(160),"" ""),CHAR(8239),"" ""),CHAR(8203),""""),""–"",""-""),""—"",""-"")), ARRAYFORMULA( TRIM( "&" SUBSTITUTE( SUBSTITUTE( SUBSTITUTE( SUBSTITUTE( SUBSTITUTE(SPLIT(TO_TEXT(template!A11),CHAR(10)),CHAR(160),"" ""), CHAR(8239),"" "" ), "&" CHAR(8203),"""" ), ""–"",""-"" ), ""—"",""-"" ) ) ), 0 ) ) ) ) "),0.0) -> 0
A5: El sustantivo | B5: 1.1.1. Nombres propios | C5: Antropónimos – hipocorísticos y diminutivos | D5: Pepe (José), Paco (Francisco), Chelo (Consuelo), Lola (Dolores) | E5: =IFERROR(__xludf.DUMMYFUNCTION("IF( C5="""","""", COUNTIF( ARRAYFORMULA( TRIM( SUBSTITUTE( SUBSTITUTE( SUBSTITUTE( SUBSTITUTE( SUBSTITUTE( SPLIT( FLATTEN( SUBSTITUTE(template!A12:A101, CHAR(10), "&"""|"") ), ""|"" ), CHAR(160),"" "" ), CHAR(8239),"" "" ), CHAR(8203),"""" ), CHAR(8211),""-"" ), CHAR(8212),""-"" ) ) "&" ), TRIM( SUBSTITUTE( SUBSTITUTE( SUBSTITUTE( SUBSTITUTE( SUBSTITUTE( TO_TEXT(C5), CHAR(160),"" "" ), CHAR(8239),"" "" ), CHAR(8203),"""" ), "&"CHAR(8211),""-"" ), CHAR(8212),""-"" ) ) ) ) "),0.0) -> 0
A6: El sustantivo | B6: 1.1.1. Nombres propios | C6: Antropónimos – hipocorísticos hispanoamericanos | D6: Chayo (Rosario), Chava (Isabel), Güicho (Luis), Pancho (Francisco) | E6: =IFERROR(__xludf.DUMMYFUNCTION("IF( C6="""","""", COUNTIF( ARRAYFORMULA( TRIM( SUBSTITUTE( SUBSTITUTE( SUBSTITUTE( SUBSTITUTE( SUBSTITUTE( SPLIT( FLATTEN( SUBSTITUTE(template!A13:A102, CHAR(10), "&"""|"") ), ""|"" ), CHAR(160),"" "" ), CHAR(8239),"" "" ), CHAR(8203),"""" ), CHAR(8211),""-"" ), CHAR(8212),""-"" ) ) "&" ), TRIM( SUBSTITUTE( SUBSTITUTE( SUBSTITUTE( SUBSTITUTE( SUBSTITUTE( TO_TEXT(C6), CHAR(160),"" "" ), CHAR(8239),"" "" ), CHAR(8203),"""" ), "&"CHAR(8211),""-"" ), CHAR(8212),""-"" ) ) ) ) "),0.0) -> 0
A7: El sustantivo | B7: 1.1.1. Nombres propios | C7: Apellidos sin artículo | D7: Fernández, González | E7: =IFERROR(__xludf.DUMMYFUNCTION("IF( C7="""","""", COUNTIF( ARRAYFORMULA( TRIM( SUBSTITUTE( SUBSTITUTE( SUBSTITUTE( SUBSTITUTE( SUBSTITUTE( SPLIT( FLATTEN( SUBSTITUTE(template!A14:A103, CHAR(10), "&"""|"") ), ""|"" ), CHAR(160),"" "" ), CHAR(8239),"" "" ), CHAR(8203),"""" ), CHAR(8211),""-"" ), CHAR(8212),""-"" ) ) "&" ), TRIM( SUBSTITUTE( SUBSTITUTE( SUBSTITUTE( SUBSTITUTE( SUBSTITUTE( TO_TEXT(C7), CHAR(160),"" "" ), CHAR(8239),"" "" ), CHAR(8203),"""" ), "&"CHAR(8211),""-"" ), CHAR(8212),""-"" ) ) ) ) "),0.0) -> 0
A8: El sustantivo | B8: 1.1.1. Nombres propios | C8: Formas de tratamiento | D8: el Sr. Fernández, (Don) Fernando | E8: =IFERROR(__xludf.DUMMYFUNCTION("IF( C8="""","""", COUNTIF( ARRAYFORMULA( TRIM( SUBSTITUTE( SUBSTITUTE( SUBSTITUTE( SUBSTITUTE( SUBSTITUTE( SPLIT( FLATTEN( SUBSTITUTE(template!A15:A104, CHAR(10), "&"""|"") ), ""|"" ), CHAR(160),"" "" ), CHAR(8239),"" "" ), CHAR(8203),"""" ), CHAR(8211),""-"" ), CHAR(8212),""-"" ) ) "&" ), TRIM( SUBSTITUTE( SUBSTITUTE( SUBSTITUTE( SUBSTITUTE( SUBSTITUTE( TO_TEXT(C8), CHAR(160),"" "" ), CHAR(8239),"" "" ), CHAR(8203),"""" ), "&"CHAR(8211),""-"" ), CHAR(8212),""-"" ) ) ) ) "),0.0) -> 0
A9: El sustantivo | B9: 1.1.1. Nombres propios | C9: Formas de tratamiento en Ecuador y Colombia | D9: Don/Doña + nombre o apellido sin connotación despectiva; uso exclusivo en ciertos estratos sociales | E9: =IFERROR(__xludf.DUMMYFUNCTION("IF( C9="""","""", COUNTIF( ARRAYFORMULA( TRIM( SUBSTITUTE( SUBSTITUTE( SUBSTITUTE( SUBSTITUTE( SUBSTITUTE( SPLIT( FLATTEN( SUBSTITUTE(template!A16:A105, CHAR(10), "&"""|"") ), ""|"" ), CHAR(160),"" "" ), CHAR(8239),"" "" ), CHAR(8203),"""" ), CHAR(8211),""-"" ), CHAR(8212),""-"" ) ) "&" ), TRIM( SUBSTITUTE( SUBSTITUTE( SUBSTITUTE( SUBSTITUTE( SUBSTITUTE( TO_TEXT(C9), CHAR(160),"" "" ), CHAR(8239),"" "" ), CHAR(8203),"""" ), "&"CHAR(8211),""-"" ), CHAR(8212),""-"" ) ) ) ) "),0.0) -> 0
A10: El sustantivo | B10: 1.1.1. Nombres propios | C10: Formas de tratamiento en República Dominicana | D10: Su merced | E10: =IFERROR(__xludf.DUMMYFUNCTION("IF( C10="""","""", COUNTIF( ARRAYFORMULA( TRIM( SUBSTITUTE( SUBSTITUTE( SUBSTITUTE( SUBSTITUTE( SUBSTITUTE( SPLIT( FLATTEN( SUBSTITUTE(template!A17:A106, CHAR(10),"&" ""|"") ), ""|"" ), CHAR(160),"" "" ), CHAR(8239),"" "" ), CHAR(8203),"""" ), CHAR(8211),""-"" ), CHAR(8212),""-"" ) ) "&" ), TRIM( SUBSTITUTE( SUBSTITUTE( SUBSTITUTE( SUBSTITUTE( SUBSTITUTE( TO_TEXT(C10), CHAR(160),"" "" ), CHAR(8239),"" "" ), CHAR(8203),"""" ), "&" CHAR(8211),""-"" ), CHAR(8212),""-"" ) ) ) ) "),0.0) -> 0
A11: El sustantivo | B11: 1.1.1. Nombres propios | C11: Topónimos – países sin artículo | D11: España, Italia | E11: =IFERROR(__xludf.DUMMYFUNCTION("IF( C11="""","""", COUNTIF( ARRAYFORMULA( TRIM( SUBSTITUTE( SUBSTITUTE( SUBSTITUTE( SUBSTITUTE( SUBSTITUTE( SPLIT( FLATTEN( SUBSTITUTE(template!A18:A107, CHAR(10),"&" ""|"") ), ""|"" ), CHAR(160),"" "" ), CHAR(8239),"" "" ), CHAR(8203),"""" ), CHAR(8211),""-"" ), CHAR(8212),""-"" ) ) "&" ), TRIM( SUBSTITUTE( SUBSTITUTE( SUBSTITUTE( SUBSTITUTE( SUBSTITUTE( TO_TEXT(C11), CHAR(160),"" "" ), CHAR(8239),"" "" ), CHAR(8203),"""" ), "&" CHAR(8211),""-"" ), CHAR(8212),""-"" ) ) ) ) "),0.0) -> 0
A12: El sustantivo | B12: 1.1.1. Nombres propios | C12: Topónimos – excepción | D12: El Salvador | E12: =IFERROR(__xludf.DUMMYFUNCTION("IF( C12="""","""", COUNTIF( ARRAYFORMULA( TRIM( SUBSTITUTE( SUBSTITUTE( SUBSTITUTE( SUBSTITUTE( SUBSTITUTE( SPLIT( FLATTEN( SUBSTITUTE(template!A19:A108, CHAR(10),"&" ""|"") ), ""|"" ), CHAR(160),"" "" ), CHAR(8239),"" "" ), CHAR(8203),"""" ), CHAR(8211),""-"" ), CHAR(8212),""-"" ) ) "&" ), TRIM( SUBSTITUTE( SUBSTITUTE( SUBSTITUTE( SUBSTITUTE( SUBSTITUTE( TO_TEXT(C12), CHAR(160),"" "" ), CHAR(8239),"" "" ), CHAR(8203),"""" ), "&" CHAR(8211),""-"" ), CHAR(8212),""-"" ) ) ) ) "),0.0) -> 0
A13: El sustantivo | B13: 1.1.1. Nombres propios | C13: Topónimos – ciudades y localidades | D13: Madrid, París, Alcalá de Henares | E13: =IFERROR(__xludf.DUMMYFUNCTION("IF( C13="""","""", COUNTIF( ARRAYFORMULA( TRIM( SUBSTITUTE( SUBSTITUTE( SUBSTITUTE( SUBSTITUTE( SUBSTITUTE( SPLIT( FLATTEN( SUBSTITUTE(template!A20:A109, CHAR(10),"&" ""|"") ), ""|"" ), CHAR(160),"" "" ), CHAR(8239),"" "" ), CHAR(8203),"""" ), CHAR(8211),""-"" ), CHAR(8212),""-"" ) ) "&" ), TRIM( SUBSTITUTE( SUBSTITUTE( SUBSTITUTE( SUBSTITUTE( SUBSTITUTE( TO_TEXT(C13), CHAR(160),"" "" ), CHAR(8239),"" "" ), CHAR(8203),"""" ), "&" CHAR(8211),""-"" ), CHAR(8212),""-"" ) ) ) ) "),0.0) -> 0
A14: El sustantivo | B14: 1.1.2. Nombres comunes | C14: Nombres de periodos temporales | D14: mediodía, tarde, noche | E14: =IFERROR(__xludf.DUMMYFUNCTION("IF( C14="""","""", COUNTIF( ARRAYFORMULA( TRIM( SUBSTITUTE( SUBSTITUTE( SUBSTITUTE( SUBSTITUTE( SUBSTITUTE( SPLIT( FLATTEN( SUBSTITUTE(template!A21:A110, CHAR(10),"&" ""|"") ), ""|"" ), CHAR(160),"" "" ), CHAR(8239),"" "" ), CHAR(8203),"""" ), CHAR(8211),""-"" ), CHAR(8212),""-"" ) ) "&" ), TRIM( SUBSTITUTE( SUBSTITUTE( SUBSTITUTE( SUBSTITUTE( SUBSTITUTE( TO_TEXT(C14), CHAR(160),"" "" ), CHAR(8239),"" "" ), CHAR(8203),"""" ), "&" CHAR(8211),""-"" ), CHAR(8212),""-"" ) ) ) ) "),0.0) -> 0
A15: El sustantivo | B15: 1.2. El género de los sustantivos | C15: Masculino en –o y femenino en –a | D15: amigo/amiga, vecino/vecina, libro/casa | E15: =IFERROR(__xludf.DUMMYFUNCTION("IF( C15="""","""", COUNTIF( ARRAYFORMULA( TRIM( SUBSTITUTE( SUBSTITUTE( SUBSTITUTE( SUBSTITUTE( SUBSTITUTE( SPLIT( FLATTEN( SUBSTITUTE(template!A22:A111, CHAR(10),"&" ""|"") ), ""|"" ), CHAR(160),"" "" ), CHAR(8239),"" "" ), CHAR(8203),"""" ), CHAR(8211),""-"" ), CHAR(8212),""-"" ) ) "&" ), TRIM( SUBSTITUTE( SUBSTITUTE( SUBSTITUTE( SUBSTITUTE( SUBSTITUTE( TO_TEXT(C15), CHAR(160),"" "" ), CHAR(8239),"" "" ), CHAR(8203),"""" ), "&" CHAR(8211),""-"" ), CHAR(8212),""-"" ) ) ) ) "),0.0) -> 0
A16: El sustantivo | B16: 1.2. El género de los sustantivos | C16: Masculino/femenino con vocal ≠ o/a | D16: el peine, la muerte | E16: =IFERROR(__xludf.DUMMYFUNCTION("IF( C16="""","""", COUNTIF( ARRAYFORMULA( TRIM( SUBSTITUTE( SUBSTITUTE( SUBSTITUTE( SUBSTITUTE( SUBSTITUTE( SPLIT( FLATTEN( SUBSTITUTE(template!A23:A112, CHAR(10),"&" ""|"") ), ""|"" ), CHAR(160),"" "" ), CHAR(8239),"" "" ), CHAR(8203),"""" ), CHAR(8211),""-"" ), CHAR(8212),""-"" ) ) "&" ), TRIM( SUBSTITUTE( SUBSTITUTE( SUBSTITUTE( SUBSTITUTE( SUBSTITUTE( TO_TEXT(C16), CHAR(160),"" "" ), CHAR(8239),"" "" ), CHAR(8203),"""" ), "&" CHAR(8211),""-"" ), CHAR(8212),""-"" ) ) ) ) "),0.0) -> 0
A17: El sustantivo | B17: 1.2. El género de los sustantivos | C17: Masculino/femenino con consonante | D17: el árbol, la catedral, la solución, el corazón | E17: =IFERROR(__xludf.DUMMYFUNCTION("IF( C17="""","""", COUNTIF( ARRAYFORMULA( TRIM( SUBSTITUTE( SUBSTITUTE( SUBSTITUTE( SUBSTITUTE( SUBSTITUTE( SPLIT( FLATTEN( SUBSTITUTE(template!A24:A113, CHAR(10),"&" ""|"") ), ""|"" ), CHAR(160),"" "" ), CHAR(8239),"" "" ), CHAR(8203),"""" ), CHAR(8211),""-"" ), CHAR(8212),""-"" ) ) "&" ), TRIM( SUBSTITUTE( SUBSTITUTE( SUBSTITUTE( SUBSTITUTE( SUBSTITUTE( TO_TEXT(C17), CHAR(160),"" "" ), CHAR(8239),"" "" ), CHAR(8203),"""" ), "&" CHAR(8211),""-"" ), CHAR(8212),""-"" ) ) ) ) "),0.0) -> 0
A18: El sustantivo | B18: 1.2. El género de los sustantivos | C18: Femenino en –o (abreviación) | D18: la moto (motocicleta), la foto (fotografía), la radio (radiodifusión) | E18: =IFERROR(__xludf.DUMMYFUNCTION("IF( C18="""","""", COUNTIF( ARRAYFORMULA( TRIM( SUBSTITUTE( SUBSTITUTE( SUBSTITUTE( SUBSTITUTE( SUBSTITUTE( SPLIT( FLATTEN( SUBSTITUTE(template!A25:A114, CHAR(10),"&" ""|"") ), ""|"" ), CHAR(160),"" "" ), CHAR(8239),"" "" ), CHAR(8203),"""" ), CHAR(8211),""-"" ), CHAR(8212),""-"" ) ) "&" ), TRIM( SUBSTITUTE( SUBSTITUTE( SUBSTITUTE( SUBSTITUTE( SUBSTITUTE( TO_TEXT(C18), CHAR(160),"" "" ), CHAR(8239),"" "" ), CHAR(8203),"""" ), "&" CHAR(8211),""-"" ), CHAR(8212),""-"" ) ) ) ) "),0.0) -> 0
A19: El sustantivo | B19: 1.2. El género de los sustantivos | C19: Heteronimia | D19: el padre/la madre, el hombre/la mujer | E19: =IFERROR(__xludf.DUMMYFUNCTION("IF( C19="""","""", COUNTIF( ARRAYFORMULA( TRIM( SUBSTITUTE( SUBSTITUTE( SUBSTITUTE( SUBSTITUTE( SUBSTITUTE( SPLIT( FLATTEN( SUBSTITUTE(template!A26:A115, CHAR(10),"&" ""|"") ), ""|"" ), CHAR(160),"" "" ), CHAR(8239),"" "" ), CHAR(8203),"""" ), CHAR(8211),""-"" ), CHAR(8212),""-"" ) ) "&" ), TRIM( SUBSTITUTE( SUBSTITUTE( SUBSTITUTE( SUBSTITUTE( SUBSTITUTE( TO_TEXT(C19), CHAR(160),"" "" ), CHAR(8239),"" "" ), CHAR(8203),"""" ), "&" CHAR(8211),""-"" ), CHAR(8212),""-"" ) ) ) ) "),0.0) -> 0
A20: El sustantivo | B20: 1.3. El número de los sustantivos | C20: Plural terminación en vocal: –s | D20: mesa/mesas, libro/libros | E20: =IFERROR(__xludf.DUMMYFUNCTION("IF( C20="""","""", N( COUNTIF( ARRAYFORMULA( TRIM( SUBSTITUTE( SPLIT( TO_TEXT(template!A27), CHAR(10) ), CHAR(160), "" "" ) ) ), TRIM( SUBSTITUTE( TO_TEXT(C20), CHAR(160), "" "" ) ) )>0 ) ) "),0.0) -> 0
A21: El sustantivo | B21: 1.3. El número de los sustantivos | C21: Plural terminación en consonante: –es | D21: árbol/árboles, pared/paredes, tenedor/tenedores | E21: =IFERROR(__xludf.DUMMYFUNCTION("IF( C21="""","""", N( COUNTIF( ARRAYFORMULA( TRIM( SUBSTITUTE( SPLIT( TO_TEXT(template!A28), CHAR(10) ), CHAR(160), "" "" ) ) ), TRIM( SUBSTITUTE( TO_TEXT(C21), CHAR(160), "" "" ) ) )>0 ) ) "),0.0) -> 0
A22: El sustantivo | B22: 1.3. El número de los sustantivos | C22: Plural terminación en –s monosílabo o aguda | D22: país/países | E22: =IFERROR(__xludf.DUMMYFUNCTION("IF( C22="""","""", N( COUNTIF( ARRAYFORMULA( TRIM( SUBSTITUTE( SPLIT( TO_TEXT(template!A29), CHAR(10) ), CHAR(160), "" "" ) ) ), TRIM( SUBSTITUTE( TO_TEXT(C22), CHAR(160), "" "" ) ) )>0 ) ) "),0.0) -> 0
A23: El sustantivo | B23: 1.3. El número de los sustantivos | C23: Significado del plural – suma de individuos iguales | D23: el coche/los coches | E23: =IFERROR(__xludf.DUMMYFUNCTION("IF( C23="""", """", N( COUNTIF( SPLIT(SUBSTITUIR(template!A30,CHAR(10),"",""),"",""), C23 )>0 ) ) "),0.0) -> 0
A24: El adjetivo | B24: 2.1.1. Adjetivos calificativos | C24: Función de complemento del nombre | D24: el chico guapo | E24: =IFERROR(__xludf.DUMMYFUNCTION("IF( C24="""", """", N( COUNTIF( SPLIT(SUBSTITUIR(template!A31,CHAR(10),"",""),"",""), C24 )>0 ) ) "),0.0) -> 0
A25: El adjetivo | B25: 2.1.1. Adjetivos calificativos | C25: Función de atributo | D25: El chico es guapo | E25: =IFERROR(__xludf.DUMMYFUNCTION("IF( C25="""", """", N( COUNTIF( SPLIT(SUBSTITUIR(template!A32,CHAR(10),"",""),"",""), C25 )>0 ) ) "),0.0) -> 0
A26: El adjetivo | B26: 2.1.1. Adjetivos calificativos | C26: Incompatibilidad con posesivos | D26: ✘ mi guapo | E26: =IFERROR(__xludf.DUMMYFUNCTION("IF( C26="""", """", N( COUNTIF( SPLIT(SUBSTITUIR(template!A33,CHAR(10),"",""),"",""), C26 )>0 ) ) "),0.0) -> 0
A27: El adjetivo | B27: 2.1.2. Adjetivos relacionales | C27: Gentilicios muy frecuentes | D27: español, francés, japonés | E27: =IFERROR(__xludf.DUMMYFUNCTION("IF( C27="""", """", N( COUNTIF( SPLIT(SUBSTITUIR(template!A34,CHAR(10),"",""),"",""), C27 )>0 ) ) "),0.0) -> 0
A28: El adjetivo | B28: 2.2. El género del adjetivo | C28: Masculino en -o / femenino en -a | D28: alto / alta | E28: =IFERROR(__xludf.DUMMYFUNCTION("IF( C28="""", """", N( COUNTIF( SPLIT(SUBSTITUIR(template!A35,CHAR(10),"",""),"",""), C28 )>0 ) ) "),0.0) -> 0
A29: El adjetivo | B29: 2.2. El género del adjetivo | C29: Masculino en consonante / femenino en -a (gentilicios) | D29: español / española, francés / francesa | E29: =IFERROR(__xludf.DUMMYFUNCTION("IF( C29="""", """", N( COUNTIF( SPLIT(SUBSTITUIR(template!A36,CHAR(10),"",""),"",""), C29 )>0 ) ) "),0.0) -> 0
A30: El adjetivo | B30: 2.2. El género del adjetivo | C30: Invariables terminados en consonante | D30: difícil, fácil | E30: =IFERROR(__xludf.DUMMYFUNCTION("IF( C30="""", """", N( COUNTIF( SPLIT(SUBSTITUIR(template!A37,CHAR(10),"",""),"",""), C30 )>0 ) ) "),0.0) -> 0
A31: El adjetivo | B31: 2.2. El género del adjetivo | C31: Gentilicios terminados en -í, -ú | D31: marroquí, hindú | E31: =IFERROR(__xludf.DUMMYFUNCTION("IF( C31="""", """", N( COUNTIF( SPLIT(SUBSTITUIR(template!A38,CHAR(10),"",""),"",""), C31 )>0 ) ) "),0.0) -> 0
A32: El adjetivo | B32: 2.3. El número del adjetivo | C32: Plural terminación en vocal: -s | D32: alto / altos, española / españolas | E32: =IFERROR(__xludf.DUMMYFUNCTION("IF( C32="""", """", N( COUNTIF( SPLIT(SUBSTITUIR(template!A39,CHAR(10),"",""),"",""), C32 )>0 ) ) "),0.0) -> 0
A33: El adjetivo | B33: 2.3. El número del adjetivo | C33: Plural terminación en consonante: -es | D33: fácil / fáciles | E33: =IFERROR(__xludf.DUMMYFUNCTION("IF( C33="""", """", N( COUNTIF( SPLIT(SUBSTITUIR(template!A40,CHAR(10),"",""),"",""), C33 )>0 ) ) "),0.0) -> 0
A34: El adjetivo | B34: 2.4. Posición del adjetivo | C34: Posición postnominal (especificativos) | D34: un chico guapo | E34: =IFERROR(__xludf.DUMMYFUNCTION("IF( C34="""", """", N( COUNTIF( SPLIT(SUBSTITUIR(template!A41,CHAR(10),"",""),"",""), C34 )>0 ) ) "),0.0) -> 0
A35: El adjetivo | B35: 2.5. Grados del adjetivo | C35: Positivo | D35: un chico guapo | E35: =IFERROR(__xludf.DUMMYFUNCTION("IF( C35="""", """", N( COUNTIF( SPLIT(SUBSTITUIR(template!A42,CHAR(10),"",""),"",""), C35 )>0 ) ) "),0.0) -> 0
A36: El adjetivo | B36: 2.5. Grados del adjetivo | C36: Superlativo absoluto con “muy” | D36: muy guapo | E36: =IFERROR(__xludf.DUMMYFUNCTION("IF( C36="""", """", N( COUNTIF( SPLIT(SUBSTITUIR(template!A43,CHAR(10),"",""),"",""), C36 )>0 ) ) "),0.0) -> 0
A37: El artículo | B37: 3.1. El artículo definido | C37: Paradigma regular | D37: el, la, los, las | E37: =IFERROR(__xludf.DUMMYFUNCTION("IF( C37="""", """", N( COUNTIF( SPLIT(SUBSTITUIR(template!A44,CHAR(10),"",""),"",""), C37 )>0 ) ) "),0.0) -> 0
A38: El artículo | B38: 3.1. El artículo definido | C38: Formas contractas | D38: al, del | E38: =IFERROR(__xludf.DUMMYFUNCTION("IF( C38="""", """", N( COUNTIF( SPLIT(SUBSTITUIR(template!A45,CHAR(10),"",""),"",""), C38 )>0 ) ) "),0.0) -> 0
A39: El artículo | B39: 3.1. El artículo definido | C39: Restricciones por tipo de sustantivo | D39: — | E39: =IFERROR(__xludf.DUMMYFUNCTION("IF( C39="""", """", N( COUNTIF( SPLIT(SUBSTITUIR(template!A46,CHAR(10),"",""),"",""), C39 )>0 ) ) "),0.0) -> 0
A40: El artículo | B40: 3.1. El artículo definido | C40: Ausencia con nombre propio de persona (regla general) | D40: — | E40: =IFERROR(__xludf.DUMMYFUNCTION("IF( C40="""", """", N( COUNTIF( SPLIT(SUBSTITUIR(template!A47,CHAR(10),"",""),"",""), C40 )>0 ) ) "),0.0) -> 0
A41: El artículo | B41: 3.1. El artículo definido | C41: Restricción por otros determinantes – primera posición del SN | D41: la otra chica / ✘ otra la chica | E41: =IFERROR(__xludf.DUMMYFUNCTION("IF( C41="""", """", N( COUNTIF( SPLIT(SUBSTITUIR(template!A48,CHAR(10),"",""),"",""), C41 )>0 ) ) "),0.0) -> 0
A42: El artículo | B42: 3.1. El artículo definido | C42: Restricción por otros determinantes – imposibilidad con posesivos y demostrativos prenominales | D42: ✘ el este libro / ✘ la mi hermana | E42: =IFERROR(__xludf.DUMMYFUNCTION("IF( C42="""", """", N( COUNTIF( SPLIT(SUBSTITUIR(template!A49,CHAR(10),"",""),"",""), C42 )>0 ) ) "),0.0) -> 0
A43: El artículo | B43: 3.1. El artículo definido | C43: Restricciones por posición sintáctica – obligatorio con sujeto en construcciones con gustar | D43: Me gusta la paella. | E43: =IFERROR(__xludf.DUMMYFUNCTION("IF( C43="""", """", N( COUNTIF( SPLIT(SUBSTITUIR(template!A50,CHAR(10),"",""),"",""), C43 )>0 ) ) "),0.0) -> 0
A44: El artículo | B44: 3.2. El artículo indefinido | C44: Paradigma regular | D44: un, una, unos, unas | E44: =IFERROR(__xludf.DUMMYFUNCTION("IF( C44="""", """", N( COUNTIF( SPLIT(SUBSTITUIR(template!A51,CHAR(10),"",""),"",""), C44 )>0 ) ) "),0.0) -> 0
A45: El artículo | B45: 3.2. El artículo indefinido | C45: Significado básico: indefinición, primera mención (referentes nuevos) | D45: Tengo un libro. | E45: =IFERROR(__xludf.DUMMYFUNCTION("IF( C45="""", """", N( COUNTIF( SPLIT(SUBSTITUIR(template!A52,CHAR(10),"",""),"",""), C45 )>0 ) ) "),0.0) -> 0
A46: El artículo | B46: 3.2. El artículo indefinido | C46: Restricciones por tipo de sustantivo – incompatibilidad con nombres propios | D46: *un Javier, *una España, *unos Correos | E46: =IFERROR(__xludf.DUMMYFUNCTION("IF( C46="""", """", N( COUNTIF( SPLIT(SUBSTITUIR(template!A53,CHAR(10),"",""),"",""), C46 )>0 ) ) "),0.0) -> 0
A47: El artículo | B47: 3.2. El artículo indefinido | C47: Restricciones por otros componentes del SN – incompatibilidad con demostrativos, numerales e indefinidos | D47: *este un amigo, *un otro amigo | E47: =IFERROR(__xludf.DUMMYFUNCTION("IF( C47="""", """", N( COUNTIF( SPLIT(SUBSTITUIR(template!A54,CHAR(10),"",""),"",""), C47 )>0 ) ) "),0.0) -> 0
A48: El artículo | B48: 3.3. Ausencia de determinación: los nombres escuetos | C48: Incompatibilidad con el verbo gustar | D48: *Me gusta paella. | E48: =IFERROR(__xludf.DUMMYFUNCTION("IF( C48="""", """", N( COUNTIF( SPLIT(SUBSTITUIR(template!A55,CHAR(10),"",""),"",""), C48 )>0 ) ) "),0.0) -> 0
A49: El artículo | B49: 3.3. Ausencia de determinación: los nombres escuetos | C49: Compatibilidad general con el verbo haber impersonal | D49: Hay árboles en la plaza. No hay leche en la nevera. | E49: =IFERROR(__xludf.DUMMYFUNCTION("IF( C49="""", """", N( COUNTIF( SPLIT(SUBSTITUIR(template!A56,CHAR(10),"",""),"",""), C49 )>0 ) ) "),0.0) -> 0
A50: Los demostrativos | B50: Forma | C50: Paradigma masculino y femenino singular/plural | D50: este, esta, estos, estas; ese, esa, esos, esas; aquel, aquella, aquellos, aquellas | E50: =IFERROR(__xludf.DUMMYFUNCTION("IF( C50="""", """", N( COUNTIF( SPLIT(SUBSTITUIR(template!A57,CHAR(10),"",""),"",""), C50 )>0 ) ) "),0.0) -> 0
A51: Los demostrativos | B51: Forma | C51: Forma del neutro singular | D51: esto, eso, aquello | E51: =IFERROR(__xludf.DUMMYFUNCTION("IF( C51="""", """", N( COUNTIF( SPLIT(SUBSTITUIR(template!A58,CHAR(10),"",""),"",""), C51 )>0 ) ) "),0.0) -> 0
A52: Los demostrativos | B52: Forma | C52: Posición inicial con verbos copulativos (ser, estar) | D52: Eso es un libro. | E52: =IFERROR(__xludf.DUMMYFUNCTION("IF( C52="""", """", N( COUNTIF( SPLIT(SUBSTITUIR(template!A59,CHAR(10),"",""),"",""), C52 )>0 ) ) "),0.0) -> 0
A53: Los demostrativos | B53: Valores / significado | C53: Déictico espacial – cercanía respecto al hablante y al oyente | D53: este libro | E53: =IFERROR(__xludf.DUMMYFUNCTION("IF( C53="""", """", N( COUNTIF( SPLIT(SUBSTITUIR(template!A60,CHAR(10),"",""),"",""), C53 )>0 ) ) "),0.0) -> 0
A54: Los demostrativos | B54: Valores / significado | C54: Déictico espacial – lejanía del hablante y del oyente | D54: ese libro, aquel árbol | E54: =IFERROR(__xludf.DUMMYFUNCTION("IF( C54="""", """", N( COUNTIF( SPLIT(SUBSTITUIR(template!A61,CHAR(10),"",""),"",""), C54 )>0 ) ) "),0.0) -> 0
A55: Los demostrativos | B55: Valores / significado | C55: Referente desconocido (objeto no identificado) | D55: ¿Qué es eso? | E55: =IFERROR(__xludf.DUMMYFUNCTION("IF( C55="""", """", N( COUNTIF( SPLIT(SUBSTITUIR(template!A62,CHAR(10),"",""),"",""), C55 )>0 ) ) "),0.0) -> 0
A56: Los demostrativos | B56: Distribución sintáctica | C56: Posición del demostrativo: delante del sustantivo | D56: — | E56: =IFERROR(__xludf.DUMMYFUNCTION("IF( C56="""", """", N( COUNTIF( SPLIT(SUBSTITUIR(template!A63,CHAR(10),"",""),"",""), C56 )>0 ) ) "),0.0) -> 0
A57: Los demostrativos | B57: Distribución sintáctica | C57: Incompatibilidad con el artículo | D57: *el este | E57: =IFERROR(__xludf.DUMMYFUNCTION("IF( C57="""", """", N( COUNTIF( SPLIT(SUBSTITUIR(template!A64,CHAR(10),"",""),"",""), C57 )>0 ) ) "),0.0) -> 0
A58: Los posesivos | B58: Forma | C58: Formas átonas. Un poseedor. Variación de número | D58: mi, mis; tu, tus; su, sus → mi libro / mis libros | E58: =IFERROR(__xludf.DUMMYFUNCTION("IF( C58="""", """", N( COUNTIF( SPLIT(SUBSTITUIR(template!A65,CHAR(10),"",""),"",""), C58 )>0 ) ) "),0.0) -> 0
A59: Los posesivos | B59: Forma | C59: Formas tónicas y átonas. Varios poseedores | D59: nuestro/a/os/as, vuestro/a/os/as, su/sus | E59: =IFERROR(__xludf.DUMMYFUNCTION("IF( C59="""", """", N( COUNTIF( SPLIT(SUBSTITUIR(template!A66,CHAR(10),"",""),"",""), C59 )>0 ) ) "),0.0) -> 0
A60: Los posesivos | B60: Forma | C60: Variación de género y número con formas tónicas de varios poseedores | D60: nuestro libro / nuestros libros, nuestra llave / nuestras llaves | E60: =IFERROR(__xludf.DUMMYFUNCTION("IF( C60="""", """", N( COUNTIF( SPLIT(SUBSTITUIR(template!A67,CHAR(10),"",""),"",""), C60 )>0 ) ) "),0.0) -> 0
A61: Los posesivos | B61: Forma | C61: Coincidencia formal de las formas átonas de 3.ª persona singular/plural | D61: su casa (de él / de ella / de ellos / de ellas) | E61: =IFERROR(__xludf.DUMMYFUNCTION("IF( C61="""", """", N( COUNTIF( SPLIT(SUBSTITUIR(template!A68,CHAR(10),"",""),"",""), C61 )>0 ) ) "),0.0) -> 0
A62: Los posesivos | B62: Distribución sintáctica | C62: Posición inicial de la forma átona | D62: mi libro / *libro mi, mi camisa roja | E62: =IFERROR(__xludf.DUMMYFUNCTION("IF( C62="""", """", N( COUNTIF( SPLIT(SUBSTITUIR(template!A69,CHAR(10),"",""),"",""), C62 )>0 ) ) "),0.0) -> 0
A63: Los posesivos | B63: Distribución sintáctica | C63: Incapacidad de aparecer solo en formas átonas | D63: ¿De quién es este libro? *Mi. *Este libro es mi. | E63: =IFERROR(__xludf.DUMMYFUNCTION("IF( C63="""", """", N( COUNTIF( SPLIT(SUBSTITUIR(template!A70,CHAR(10),"",""),"",""), C63 )>0 ) ) "),0.0) -> 0
A64: Los posesivos | B64: Distribución sintáctica | C64: Incompatibilidad con adjetivos y con artículo en formas átonas | D64: *mi interesante, *la mi amiga | E64: =IFERROR(__xludf.DUMMYFUNCTION("IF( C64="""", """", N( COUNTIF( SPLIT(SUBSTITUIR(template!A71,CHAR(10),"",""),"",""), C64 )>0 ) ) "),0.0) -> 0
A65: Los posesivos | B65: Distribución sintáctica | C65: Incompatibilidad con el verbo haber | D65: *Hay mis amigos. | E65: =IFERROR(__xludf.DUMMYFUNCTION("IF( C65="""", """", N( COUNTIF( SPLIT(SUBSTITUIR(template!A72,CHAR(10),"",""),"",""), C65 )>0 ) ) "),0.0) -> 0
A66: Los cuantificadores | B66: 6.1. Cuantificadores propios – Numerales | C66: Cardinales | D66: dos, catorce, trescientos, quince mil | E66: =IFERROR(__xludf.DUMMYFUNCTION("IF( C66="""", """", N( COUNTIF( SPLIT(SUBSTITUIR(template!A73,CHAR(10),"",""),"",""), C66 )>0 ) ) "),0.0) -> 0
A67: Los cuantificadores | B67: 6.1. Cuantificadores propios – Numerales | C67: Variación de género y de número | D67: doscientas personas, doscientos euros | E67: =IFERROR(__xludf.DUMMYFUNCTION("IF( C67="""", """", N( COUNTIF( SPLIT(SUBSTITUIR(template!A74,CHAR(10),"",""),"",""), C67 )>0 ) ) "),0.0) -> 0
A68: Los cuantificadores | B68: 6.1. Cuantificadores propios – Numerales | C68: Ordinales (hasta 10.º) | D68: primero / primera, segundo / segunda | E68: =IFERROR(__xludf.DUMMYFUNCTION("IF( C68="""", """", N( COUNTIF( SPLIT(SUBSTITUIR(template!A75,CHAR(10),"",""),"",""), C68 )>0 ) ) "),0.0) -> 0
A69: Los cuantificadores | B69: 6.1. Cuantificadores propios – No universales | C69: Afirmativos: poco, mucho | D69: — | E69: =IFERROR(__xludf.DUMMYFUNCTION("IF( C69="""", """", N( COUNTIF( SPLIT(SUBSTITUIR(template!A76,CHAR(10),"",""),"",""), C69 )>0 ) ) "),0.0) -> 0
A70: Los cuantificadores | B70: 6.1. Cuantificadores propios – No universales | C70: Variación de género y número | D70: Hace mucho calor. Tengo muchos amigos. Bastante. | E70: =IFERROR(__xludf.DUMMYFUNCTION("IF( C70="""", """", N( COUNTIF( SPLIT(SUBSTITUIR(template!A77,CHAR(10),"",""),"",""), C70 )>0 ) ) "),0.0) -> 0
A71: Los cuantificadores | B71: 6.1. Cuantificadores propios – No universales | C71: Variación de número | D71: Hay bastante dinero. Tenemos bastantes problemas. | E71: =IFERROR(__xludf.DUMMYFUNCTION("IF( C71="""", """", N( COUNTIF( SPLIT(SUBSTITUIR(template!A78,CHAR(10),"",""),"",""), C71 )>0 ) ) "),0.0) -> 0
A72: Los cuantificadores | B72: 6.2. Cuantificadores focales o presuposicionales | C72: Incluyentes: también, tampoco | D72: Yo también soy alemán. Yo tampoco voy. | E72: =IFERROR(__xludf.DUMMYFUNCTION("IF( C72="""", """", N( COUNTIF( SPLIT(SUBSTITUIR(template!A79,CHAR(10),"",""),"",""), C72 )>0 ) ) "),0.0) -> 0
A73: El pronombre | B73: 7.1.1. Pronombre sujeto – Forma | C73: Paradigma de las tres personas gramaticales | D73: yo, tú, él, nosotros, vosotros, ellos | E73: =IFERROR(__xludf.DUMMYFUNCTION("IF( C73="""", """", N( COUNTIF( SPLIT(SUBSTITUIR(template!A80,CHAR(10),"",""),"",""), C73 )>0 ) ) "),0.0) -> 0
A74: El pronombre | B74: 7.1.1. Pronombre sujeto – Forma | C74: Variación de género (3.ª persona singular y plural) | D74: él/ella, ellos/ellas; nosotros/nosotras; vosotros/vosotras | E74: =IFERROR(__xludf.DUMMYFUNCTION("IF( C74="""", """", N( COUNTIF( SPLIT(SUBSTITUIR(template!A81,CHAR(10),"",""),"",""), C74 )>0 ) ) "),0.0) -> 0
A75: El pronombre | B75: 7.1.1. Pronombre sujeto – Forma | C75: [Zonas voseantes Hispanoamérica] Forma vos (2.ª singular) | D75: Coexistencia del tuteo con alternancia de formas con vos | E75: =IFERROR(__xludf.DUMMYFUNCTION("IF( C75="""", """", N( COUNTIF( SPLIT(SUBSTITUIR(template!A82,CHAR(10),"",""),"",""), C75 )>0 ) ) "),0.0) -> 0
A76: El pronombre | B76: 7.1.1. Pronombre sujeto – Forma | C76: [México, excepto Chiapas y El Caribe] Uso exclusivo del tuteo | D76: — | E76: =IFERROR(__xludf.DUMMYFUNCTION("IF( C76="""", """", N( COUNTIF( SPLIT(SUBSTITUIR(template!A83,CHAR(10),"",""),"",""), C76 )>0 ) ) "),0.0) -> 0
A77: El pronombre | B77: 7.1.1. Pronombre sujeto – Forma | C77: Forma usted/ustedes (Hispanoamérica, España: variedades meridionales y Canarias) | D77: Uso exclusivo de ustedes para 2.ª plural; ausencia de vosotros/as | E77: =IFERROR(__xludf.DUMMYFUNCTION("IF( C77="""", """", N( COUNTIF( SPLIT(SUBSTITUIR(template!A84,CHAR(10),"",""),"",""), C77 )>0 ) ) "),0.0) -> 0
A78: El pronombre | B78: 7.1.1. Pronombre sujeto – Presencia/ausencia | C78: Ausencia general: sujeto innecesario/inaceptable (relación temática con el predicado) | D78: Estudio español. | E78: =IFERROR(__xludf.DUMMYFUNCTION("IF( C78="""", """", N( COUNTIF( SPLIT(SUBSTITUIR(template!A85,CHAR(10),"",""),"",""), C78 )>0 ) ) "),0.0) -> 0
A79: El pronombre | B79: 7.1.1. Pronombre sujeto – Presencia/ausencia | C79: [Hispanoamérica] Tendencia a usar pronombres sujetos | D79: Yo estudio español. | E79: =IFERROR(__xludf.DUMMYFUNCTION("IF( C79="""", """", N( COUNTIF( SPLIT(SUBSTITUIR(template!A86,CHAR(10),"",""),"",""), C79 )>0 ) ) "),0.0) -> 0
A80: El pronombre | B80: 7.1.1. Pronombre sujeto – Presencia/ausencia | C80: Presencia con valor de contraste | D80: Yo soy Clara, ¿y tú? | E80: =IFERROR(__xludf.DUMMYFUNCTION("IF( C80="""", """", N( COUNTIF( SPLIT(SUBSTITUIR(template!A87,CHAR(10),"",""),"",""), C80 )>0 ) ) "),0.0) -> 0
A81: El pronombre | B81: 7.1.1. Pronombre sujeto – Presencia/ausencia | C81: Ausencia en oraciones impersonales con haber | D81: Hay mucha gente. | E81: =IFERROR(__xludf.DUMMYFUNCTION("IF( C81="""", """", N( COUNTIF( SPLIT(SUBSTITUIR(template!A88,CHAR(10),"",""),"",""), C81 )>0 ) ) "),0.0) -> 0
A82: El pronombre | B82: 7.1.1. Pronombre sujeto – Valores/significado | C82: Referente humano, uso del demostrativo para cosas | D82: Hay una ventana. Esta (ventana) es grande. | E82: =IFERROR(__xludf.DUMMYFUNCTION("IF( C82="""", """", N( COUNTIF( SPLIT(SUBSTITUIR(template!A89,CHAR(10),"",""),"",""), C82 )>0 ) ) "),0.0) -> 0
A83: El pronombre | B83: 7.1.1. Pronombre sujeto – Valores/significado | C83: Referencia a participantes del discurso – yo y tú | D83: — | E83: =IFERROR(__xludf.DUMMYFUNCTION("IF( C83="""", """", N( COUNTIF( SPLIT(SUBSTITUIR(template!A90,CHAR(10),"",""),"",""), C83 )>0 ) ) "),0.0) -> 0
A84: El pronombre | B84: 7.1.1. Pronombre sujeto – Valores/significado | C84: Nosotros inclusivo (incluye al oyente): yo + tú (+ terceros) | D84: — | E84: =IFERROR(__xludf.DUMMYFUNCTION("IF( C84="""", """", N( COUNTIF( SPLIT(SUBSTITUIR(template!A91,CHAR(10),"",""),"",""), C84 )>0 ) ) "),0.0) -> 0
A85: El pronombre | B85: 7.1.1. Pronombre sujeto – Valores/significado | C85: Nosotros no inclusivo (excluye al oyente): yo + él/ella/ellos/ellas | D85: — | E85: =IFERROR(__xludf.DUMMYFUNCTION("IF( C85="""", """", N( COUNTIF( SPLIT(SUBSTITUIR(template!A92,CHAR(10),"",""),"",""), C85 )>0 ) ) "),0.0) -> 0
A86: El pronombre | B86: 7.1.1. Pronombre sujeto – Valores/significado | C86: Vosotros: oyente(s) tú + tú (+ terceros) | D86: — | E86: =IFERROR(__xludf.DUMMYFUNCTION("IF( C86="""", """", N( COUNTIF( SPLIT(SUBSTITUIR(template!A93,CHAR(10),"",""),"",""), C86 )>0 ) ) "),0.0) -> 0
A87: El pronombre | B87: 7.1.2. Pronombres átonos de OD | C87: Presencia/ausencia – ausencia con haber | D87: ¿Hay parques en tu barrio? Sí, hay. | E87: =IFERROR(__xludf.DUMMYFUNCTION("IF( C87="""", """", N( COUNTIF( SPLIT(SUBSTITUIR(template!A94,CHAR(10),"",""),"",""), C87 )>0 ) ) "),0.0) -> 0
A88: El pronombre | B88: 7.1.2. Pronombres átonos de OD | C88: Presencia/ausencia – ausencia en respuestas sin determinante/ni cuantificador (interpretación inespecífica) | D88: ¿Tienes coche? No, no tengo. | E88: =IFERROR(__xludf.DUMMYFUNCTION("IF( C88="""", """", N( COUNTIF( SPLIT(SUBSTITUIR(template!A95,CHAR(10),"",""),"",""), C88 )>0 ) ) "),0.0) -> 0
A89: El pronombre | B89: 7.1.3. Pronombres átonos de OI | C89: Forma – 1.ª persona singular | D89: Me gusta el cine. | E89: =IFERROR(__xludf.DUMMYFUNCTION("IF( C89="""", """", N( COUNTIF( SPLIT(SUBSTITUIR(template!A96,CHAR(10),"",""),"",""), C89 )>0 ) ) "),0.0) -> 0
A90: El pronombre | B90: 7.1.3. Pronombres átonos de OI | C90: Valores/significado – experimentante semántico, no sujeto gramatical (gustar) | D90: Me gustan los coches. | E90: =IFERROR(__xludf.DUMMYFUNCTION("IF( C90="""", """", N( COUNTIF( SPLIT(SUBSTITUIR(template!A97,CHAR(10),"",""),"",""), C90 )>0 ) ) "),0.0) -> 0
A91: El pronombre | B91: 7.1.4. Valores de se | C91: Forma – pronombre personal, única para singular y plural | D91: — | E91: =IFERROR(__xludf.DUMMYFUNCTION("IF( C91="""", """", N( COUNTIF( SPLIT(SUBSTITUIR(template!A98,CHAR(10),"",""),"",""), C91 )>0 ) ) "),0.0) -> 0
A92: El pronombre | B92: 7.1.4. Valores de se | C92: Valores/significado – pronombre reflexivo | D92: Levantarse, peinarse | E92: =IFERROR(__xludf.DUMMYFUNCTION("IF( C92="""", """", N( COUNTIF( SPLIT(SUBSTITUIR(template!A99,CHAR(10),"",""),"",""), C92 )>0 ) ) "),0.0) -> 0
A93: El pronombre | B93: 7.1.4. Valores de se | C93: [Hispanoamérica] Tendencia a usar formas reflexivas | D93: desayunarse, tardarse, amanecerse, robarse | E93: =IFERROR(__xludf.DUMMYFUNCTION("IF( C93="""", """", N( COUNTIF( SPLIT(SUBSTITUIR(template!A100,CHAR(10),"",""),"",""), C93 )>0 ) ) "),0.0) -> 0
A94: El pronombre | B94: 7.2. Los relativos – Que | C94: En relativas especificativas con antecedente expreso | D94: El libro que lee es muy interesante. | E94: =IFERROR(__xludf.DUMMYFUNCTION("IF( C94="""", """", N( COUNTIF( SPLIT(SUBSTITUIR(template!A101,CHAR(10),"",""),"",""), C94 )>0 ) ) "),0.0) -> 0
A95: El pronombre | B95: 7.2. Los relativos – Que | C95: Invariable, carente de flexión. Átono, proclítico | D95: la profesora que tengo / las casas que veo | E95: =IFERROR(__xludf.DUMMYFUNCTION("IF( C95="""", """", N( COUNTIF( SPLIT(SUBSTITUIR(template!A102,CHAR(10),"",""),"",""), C95 )>0 ) ) "),0.0) -> 0
A96: El pronombre | B96: 7.2. Los relativos – Que | C96: Naturaleza del antecedente: sustantivo (+/– humano) | D96: El libro que lee / La profesora que tengo | E96: =IFERROR(__xludf.DUMMYFUNCTION("IF( C96="""", """", N( COUNTIF( SPLIT(SUBSTITUIR(template!A103,CHAR(10),"",""),"",""), C96 )>0 ) ) "),0.0) -> 0
A97: El pronombre | B97: 7.2. Los relativos – Que | C97: Función de sujeto y de OD, con antecedente obligatorio | D97: La profesora que tengo me gusta mucho. / Vivo en una casa que tiene tres habitaciones. | E97: =IFERROR(__xludf.DUMMYFUNCTION("IF( C97="""", """", N( COUNTIF( SPLIT(SUBSTITUIR(template!A104,CHAR(10),"",""),"",""), C97 )>0 ) ) "),0.0) -> 0
A98: El pronombre | B98: 7.3. Los interrogativos – Qué | C98: Tónico con acento gráfico. Posición inicial de la oración. Invariable | D98: ¿Qué estudias? ¿Qué libro lees? | E98: =IFERROR(__xludf.DUMMYFUNCTION("IF( C98="""", """", N( COUNTIF( SPLIT(SUBSTITUIR(template!A105,CHAR(10),"",""),"",""), C98 )>0 ) ) "),0.0) -> 0
A99: El pronombre | B99: 7.3. Los interrogativos – Qué | C99: Pregunta por objetos o acciones (– humano) | D99: ¿Qué es eso?, ¿Qué haces? | E99: =IFERROR(__xludf.DUMMYFUNCTION("IF( C99="""", """", N( COUNTIF( SPLIT(SUBSTITUIR(template!A106,CHAR(10),"",""),"",""), C99 )>0 ) ) "),0.0) -> 0
A100: El pronombre | B100: 7.3. Los interrogativos – Quién / quiénes | C100: Forma singular/plural. Tónico con acento gráfico. Posición inicial | D100: ¿Quién es esa chica? | E100: =IFERROR(__xludf.DUMMYFUNCTION("IF( C100="""", """", N( COUNTIF( SPLIT(SUBSTITUIR(template!A107,CHAR(10),"",""),"",""), C100 )>0 ) ) "),0.0) -> 0
...

Sheet Pronunciation
A1: Reference: https://cvc.cervantes.es/ensenanza/biblioteca_ele/plan_curricular/niveles/03_pronunciacion_inventario_a1-a2.htm
A2: Section | B2: Subsection / Item | C2: Topic | D2: Example / Notes
A3: 1. La base de articulación | B3: 1.1. Caracterización general del español | C3: Modo normal de fonación
A4: 1. La base de articulación | B4: 1.1. Caracterización general del español | C4: Grado de tensión | D4: Menor que francés, superior al inglés
A5: 1. La base de articulación | B5: 1.1. Caracterización general del español | C5: Pureza de las vocales | D5: No hay vocales anteriores redondeadas
A6: 1. La base de articulación | B6: 1.1. Caracterización general del español | C6: Ausencia de africación en las consonantes
A7: 1. La base de articulación | B7: 1.1. Caracterización general del español | C7: Mantenimiento del timbre en vocales inacentuadas
A8: 1. La base de articulación | B8: 1.1. Caracterización general del español | C8: Movimiento de labios | D8: Relativamente marcado
A9: 1. La base de articulación | B9: 1.1. Caracterización general del español | C9: Nasalización | D9: Poco constante, sin relevancia fonológica
A10: 1. La base de articulación | B10: 1.1. Caracterización general del español | C10: Base articulatoria creciente | D10: Tendencia a la sílaba abierta
A11: 1. La base de articulación | B11: 1.1. Caracterización general del español | C11: Base central-anterior | D11: Predominio de alveolares y palatales
A12: 1. La base de articulación | B12: Precisiones sobre «acento idiomático» | C12: Noción del acento | D12: Hábitos articulatorios, procedencia geográfica/sociocultural
A13: 1. La base de articulación | B13: Precisiones sobre «acento idiomático» | C13: Variedades | D13: Información sobre articulación en el mundo hispánico
A14: 2. La entonación | B14: 2.1. Segmentación en unidades melódicas | C14: Correspondencia con puntuación | D14: Punto
A15: 2. La entonación | B15: 2.1. Segmentación en unidades melódicas | C15: Correspondencia con puntuación | D15: Coma
A16: 2. La entonación | B16: 2.1. Segmentación en unidades melódicas | C16: Correspondencia con puntuación | D16: Signos de interrogación y exclamación
A17: 2. La entonación | B17: 2.1. Segmentación en unidades melódicas | C17: Extensión de la unidad | D17: Unidad mínima: palabra monosilábica (¿Quién ha venido? – Yo.)
A18: 2. La entonación | B18: 2.1. Segmentación en unidades melódicas | C18: Extensión de la unidad | D18: Unidades de 5–10 sílabas: predomina 7–8 (Trabaja en un banco.)
A19: 2. La entonación | B19: 2.1. Segmentación en unidades melódicas | C19: Extensión de la unidad | D19: Escasez de <5 y >10–15 sílabas (¿Qué? / No creo que tengas razón…)
... A89: 4. Ritmo, pausas y tiempo | B89: 4.2.3. Pausas llenas | C89: Interjecciones | D89: ¡a:!
A90: 4. Ritmo, pausas y tiempo | B90: 4.2.4. Grupo fónico | C90: Concepto y extensión
A91: 5. Los fonemas | B91: 5.1.1. Vocales | C91: Cualidad /a, e, i, o, u/ | D91: Claridad y precisión
A92: 5. Los fonemas | B92: 5.1.1. Vocales | C92: Comparación | D92: Otras lenguas: francés, inglés, alemán
A93: 5. Los fonemas | B93: 5.1.1. Vocales | C93: Posición de lengua | D93: Vocal a (central), e/i (anteriores), o/u (posteriores)
A94: 5. Los fonemas | B94: 5.1.1. Vocales | C94: Abertura mandibular | D94: a (abierta), e/o (medias), i/u (cerradas)
A95: 5. Los fonemas | B95: 5.1.1. Vocales | C95: Ataque suave | D95: No hay golpe de glotis
A96: 5. Los fonemas | B96: 5.1.2. Comparación de vocales | C96: A | D96: Central (caro, rápido…)
A97: 5. Los fonemas | B97: 5.1.2. Comparación de vocales | C97: I | D97: Similar al francés vie, menos cerrada
A98: 5. Los fonemas | B98: 5.1.2. Comparación de vocales | C98: E | D98: No tan cerrada, no diptongada
A99: 5. Los fonemas | B99: 5.1.2. Comparación de vocales | C99: O | D99: No cerrada, no diptongada como inglés note
A100: 5. Los fonemas | B100: 5.1.2. Comparación de vocales | C100: U | D100: Similar al francés tout
A101: 5. Los fonemas | B101: 5.1.3. Diptongos | C101: Crecientes | D101: fiasco, viejo, labio, guante
A102: 5. Los fonemas | B102: 5.1.3. Diptongos | C102: Decrecientes | D102: bailar, aula, ley, euro
... A125: 5. Los fonemas | B125: 5.3.2. Sirrema | C125: Pronombre átono + verbo | D125: la vi ayer > laviayer

Sheet Ortography
A1: Section | B1: Subsection / Item | C1: Topic | D1: Example / Notes
A2: 1. Ortografía de letras y palabras | B2: 1.1. Abecedario | C2: Nombre de las letras del abecedario o alfabeto
A3: 1. Ortografía de letras y palabras | B3: 1.1. Abecedario | C3: Letras con varios nombres en español | D3: b: be, be alta, be larga
A4: 1. Ortografía de letras y palabras | B4: 1.1. Abecedario | C4: Letras con varios nombres en español | D4: r/rr: ere, erre
A5: 1. Ortografía de letras y palabras | B5: 1.1. Abecedario | C5: Letras con varios nombres en español | D5: v: uve, ve, ve baja, ve corta
A6: 1. Ortografía de letras y palabras | B6: 1.1. Abecedario | C6: Letras con varios nombres en español | D6: w: uve doble, ve doble, doble uve, doble u
A7: 1. Ortografía de letras y palabras | B7: 1.1. Abecedario | C7: Letras con varios nombres en español | D7: y: i griega, ye
A8: 1. Ortografía de letras y palabras | B8: 1.1. Abecedario | C8: Letras con varios nombres en español | D8: z: zeta
A9: 1. Ortografía de letras y palabras | B9: 1.1. Abecedario | C9: Plural de las letras | D9: los eses, los ces – “Esta palabra tiene dos lés”
A10: 1. Ortografía de letras y palabras | B10: 1.1. Abecedario | C10: Correspondencia de más de una letra para un sonido | D10: b/v → /b/
A11: 1. Ortografía de letras y palabras | B11: 1.1. Abecedario | C11: Correspondencia de más de una letra para un sonido | D11: g/e, g/i → /x/
A12: 1. Ortografía de letras y palabras | B12: 1.1. Abecedario | C12: Correspondencia de más de una letra para un sonido | D12: k/qu + e,a,o,u → /k/
A13: 1. Ortografía de letras y palabras | B13: 1.1. Abecedario | C13: Correspondencia de una letra para más de un sonido | D13: v → /u/, /b/
A14: 1. Ortografía de letras y palabras | B14: 1.1. Abecedario | C14: Correspondencia de una letra para más de un sonido | D14: y → /ʝ/, /i/
A15: 1. Ortografía de letras y palabras | B15: 1.1. Abecedario | C15: Dígrafos | D15: ch, ll
A16: 1. Ortografía de letras y palabras | B16: 1.1. Abecedario | C16: Deletreo
A17: 1. Ortografía de letras y palabras | B17: 1.1. Abecedario | C17: Escasa frecuencia de aparición de consonantes idénticas contiguas en español
A18: 1. Ortografía de letras y palabras | B18: 1.2. Vocales | C18: Letras a, e, i, o, u – representación gráfica | D18: /a/, /e/, /i/, /o/, /u/
A19: 1. Ortografía de letras y palabras | B19: 1.2. Vocales | C19: Susceptibles de llevar tilde | D19: (en oposición a las consonantes)
A20: 1. Ortografía de letras y palabras | B20: 1.2. Vocales | C20: Formas contractas | D20: al, del
A21: 1. Ortografía de letras y palabras | B21: 1.2. Vocales | C21: Conjunción e/y | D21: *Hablo español e inglés* / *Hablo español y inglés*
A22: 1. Ortografía de letras y palabras | B22: 1.2. Vocales | C22: Conjunción o/u | D22: *Tiene diez o once libros* / *Tiene diez u once libros*
A23: 1. Ortografía de letras y palabras | B23: 1.3. Consonantes | C23: 1.3.1. Letra b | D23: Representación gráfica del fonema labial sonoro /b/
A24: 1. Ortografía de letras y palabras | B24: 1.3. Consonantes | C24: 1.3.1. Letra v | D24: Representación gráfica del fonema labial sonoro /b/
A25: 1. Ortografía de letras y palabras | B25: 1.3. Consonantes | C25: 1.3.1. Letra v | D25: Presente de indicativo de *ir*
A26: 1. Ortografía de letras y palabras | B26: 1.3. Consonantes | C26: 1.3.1. Letra w | D26: Representación gráfica del fonema semiconsonántico /w/ en voces no adaptadas | E26: sándwich, web
A27: 1. Ortografía de letras y palabras | B27: 1.3. Consonantes | C27: 1.3.2. Letra c | D27: Representación gráfica del fonema oclusivo velar sordo /k/ | E27: ante a, o, u, consonante y en posición final de sílaba (calle, compañero, cuatro, clase, actor)
A28: 1. Ortografía de letras y palabras | B28: 1.3. Consonantes | C28: 1.3.2. Letra c | D28: Representación gráfica del fonema fricativo interdental sordo /θ/ | E28: ante e, i (cena, cine)
A29: 1. Ortografía de letras y palabras | B29: 1.3. Consonantes | C29: 1.3.2. Letra c | D29: Excepción | E29: zeta
A30: 1. Ortografía de letras y palabras | B30: 1.3. Consonantes | C30: 1.3.2. Letra c | D30: Seseo – representación del fonema predorsal fricativo sordo /s/ | E30: (Hispanoamérica, suroeste de España, Canarias)
A31: 1. Ortografía de letras y palabras | B31: 1.3. Consonantes | C31: 1.3.2. Letra c | D31: Posibilidad de duplicación | E31: cc en español (lección, dirección, diccionario)
A32: 1. Ortografía de letras y palabras | B32: 1.3. Consonantes | C32: 1.3.2. Letra k | D32: Representación gráfica del fonema oclusivo velar sordo /k/ | E32: kilómetro
A33: 1. Ortografía de letras y palabras | B33: 1.3. Consonantes | C33: 1.3.2. Letra q | D33: Dígrafo qu ante e,i → /k/ | E33: pequeño, quien
A34: 1. Ortografía de letras y palabras | B34: 1.3. Consonantes | C34: 1.3.2. Letra z | D34: Representación gráfica del fonema fricativo interdental /θ/ | E34: ante a, o, u (zapatos, brazo, azul)
A35: 1. Ortografía de letras y palabras | B35: 1.3. Consonantes | C35: 1.3.2. Letra z | D35: Excepción | E35: zeta
A36: 1. Ortografía de letras y palabras | B36: 1.3. Consonantes | C36: 1.3.2. Letra z | D36: Seseo – /s/ | E36: (Hispanoamérica, suroeste de España, Canarias)
A37: 1. Ortografía de letras y palabras | B37: 1.3. Consonantes | C37: 1.3.2. Letra z | D37: Posición final de sílaba o palabra | E37: mezquita, lápiz
... A42: 1. Ortografía de letras y palabras | B42: 1.3. Consonantes | C42: 1.3.3. Letra j | D42: Representación gráfica del fonema velar sordo /x/ | E42: Juan, extranjero, reloj
A43: 1. Ortografía de letras y palabras | B43: 1.3. Consonantes | C43: 1.3.4. Letra h | D43: Correspondencia de la h con ausencia de sonido
A44: 1. Ortografía de letras y palabras | B44: 1.3. Consonantes | C44: 1.3.4. Letra h | D44: Posición de la letra – inicio de palabra | E44: hermano, hijo
A45: 1. Ortografía de letras y palabras | B45: 1.3. Consonantes | C45: 1.3.4. Letra h | D45: Palabras procedentes de voces latinas | E45: con f inicial (hacer, hijo)
A46: 1. Ortografía de letras y palabras | B46: 1.3. Consonantes | C46: 1.3.5. Letra y | D46: Representación del fonema vocálico /i/ | E46: diptongos, triptongos, conjunción (hay, soy, Uruguay)
A47: 1. Ortografía de letras y palabras | B47: 1.3. Consonantes | C47: 1.3.5. Letra y | D47: Representación del fonema palatal sonoro /ʝ/ | E47: ante vocal (yo, ayer, desayuno)
A48: 1. Ortografía de letras y palabras | B48: 1.3. Consonantes | C48: 1.3.5. Letra y | D48: Conjunción | E48: Sustitución de “y” por “e” ante palabra con /i/ inicial (Pedro e Inés)
A49: 1. Ortografía de letras y palabras | B49: 1.3. Consonantes | C49: 1.3.5. Dígrafo ll | D49: Representación del fonema palatal lateral sonoro /ʎ/ | E49: billete, llevar
A50: 1. Ortografía de letras y palabras | B50: 1.3. Consonantes | C50: 1.3.6. Letra m | D50: Representación del fonema labial nasal /m/ | E50: en inicio de palabra o sílaba (madre, número)
A51: 1. Ortografía de letras y palabras | B51: 1.3. Consonantes | C51: 1.3.6. Letra n | D51: Representación del fonema dental nasal /n/ | E51: ante b, p, v (nombre, tiempo)
A52: 1. Ortografía de letras y palabras | B52: 1.3. Consonantes | C52: 1.3.6. Letra ñ | D52: Representación del fonema palatal nasal /ɲ/ | E52: en inicio de sílaba (compañero, pequeño, año)
A53: 1. Ortografía de letras y palabras | B53: 1.3. Consonantes | C53: 1.3.7. Letra p | D53: Representación del fonema labial oclusivo sordo /p/ | E53: padre, aprender
A54: 1. Ortografía de letras y palabras | B54: 1.3. Consonantes | C54: 1.3.7. Letra p | D54: Grupo ps- | E54: Soy psicólogo
A55: 1. Ortografía de letras y palabras | B55: 1.3. Consonantes | C55: 1.3.8. Letra r | D55: Representación del fonema vibrante simple /ɾ/ | E55: intervocálica, después de consonantes (número, madre, francés…)
... A57: 1. Ortografía de letras y palabras | B57: 1.3. Consonantes | C57: 1.3.8. Dígrafo rr | D57: Representación del fonema vibrante múltiple /r/ | E57: intervocálica (marrón)
A58: 1. Ortografía de letras y palabras | B58: 1.3. Consonantes | C58: 1.3.9. Letra s | D58: Representación del fonema fricativo predorsal sordo /s/
A59: 1. Ortografía de letras y palabras | B59: 1.3. Consonantes | C59: 1.3.9. Letra x | D59: Representación del grupo /ks/ o /gs/ | E59: en posición intervocálica o final de sílaba/palabra (taxista, exposición, relax)
A60: 1. Ortografía de letras y palabras | B60: 1.3. Consonantes | C60: 1.3.9. Letra x | D60: Representación del fonema fricativo sordo /x/ | E60: en voces como México, Oaxaca, Texas
A61: 1. Ortografía de letras y palabras | B61: 1.3. Consonantes | C61: 1.3.10. Letra t | D61: Representación del fonema dental oclusivo sordo /t/ | E61: teatro, contento
A62: 1. Ortografía de letras y palabras | B62: 1.3. Consonantes | C62: 1.3.10. Letra d | D62: Representación del fonema dental oclusivo sonoro /d/ | E62: teatro, contento

Sheet Chapter Status
A1: Due Date | B1: Person/ Status | C1: Type | D1: Name | E1: dashed-name | F1: QA | G1: PR Links/ notes
B2: 0 | C2: Chapter | D2: Welcome to A1 Professional Spanish | E2: es-a1-chapter-welcome-to-a1-professional-spanish | F2: FALSE
A3: 45940 | B3: Rafael | C3: Module | D3: Introduction and Certification Overview | E3: es-a1-module-introduction-and-certification-overview | F3: FALSE | G3: https://github.com/freeCodeCamp/freeCodeCamp/pull/62424
B4: Merged 🎉 | C4: Learn | D4: Certification Introduction | E4: es-a1-learn-certification-introduction | F4: TRUE
B5: 1 | C5: Chapter | D5: Spanish Fundamentals | E5: es-a1-chapter-spanish-fundamentals | F5: FALSE
A6: 45954 | B6: Estefania | C6: Module | D6: Letters, Sounds and First Numbers | E6: es-a1-module-letters-sounds-and-first-numbers | F6: FALSE | G6: https://github.com/freeCodeCamp/freeCodeCamp/pull/62719 rename
B7: Merged 🎉 | C7: Learn | D7: Vowels | E7: es-a1-learn-vowels | F7: TRUE
B8: Merged 🎉 | C8: Learn | D8: Consonants and Special Characters | E8: es-a1-learn-consonants-and-special-characters | F8: TRUE
B9: Merged 🎉 | C9: Practice | D9: The Spanish Alphabet Practice | E9: es-a1-practice-the-alphabet | F9: TRUE
B10: Merged 🎉 | C10: Learn | D10: The First Ten Numbers | E10: es-a1-learn-the-first-ten-numbers | F10: TRUE | G10: https://github.com/freeCodeCamp/freeCodeCamp/pull/64018
B11: Merged 🎉 | C11: Practice | D11: The First Ten Numbers Practice | E11: es-a1-practice-the-first-ten-numbers | F11: TRUE
B12: Merged 🎉 | C12: Review | D12: Spanish Fundamentals Review | E12: es-a1-review-spanish-fundamentals | F12: TRUE
B13: Merged 🎉 | C13: Quiz | D13: Spanish Fundamentals Quiz | E13: es-a1-quiz-spanish-fundamentals | F13: TRUE
B14: 2 | C14: Chapter | D14: Greetings and Introductions | E14: es-a1-chapter-greetings-and-introductions | F14: FALSE
A15: 45940 | B15: Nielda | C15: Module | D15: Greetings and Farewells | E15: es-a1-module-greetings-and-farewells | F15: FALSE | G15: https://github.com/freeCodeCamp/freeCodeCamp/pull/62201
B16: Merged 🎉 | C16: Warm-up | D16: Greetings and Farewells Basics | E16: es-a1-warm-up-greetings-and-farewells-basics | F16: TRUE
B17: Merged 🎉 | C17: Learn | D17: Greetings During the Day | E17: es-a1-learn-greetings-during-the-day | F17: TRUE
B18: Merged 🎉 | C18: Practice | D18: Greetings and Farewells Practice | E18: es-a1-practice-greetings-and-farewells | F18: TRUE
B19: Merged 🎉 | C19: Review | D19: Greetings and Farewells Review | E19: es-a1-review-greetings-and-farewells | F19: TRUE
B20: Merged 🎉 | C20: Quiz | D20: Greetings and Farewells Quiz | E20: es-a1-quiz-greetings-and-farewells | F20: TRUE
A21: 45943 | B21: Rafael | C21: Module | D21: Introducing Yourself | E21: es-a1-module-introducing-yourself | F21: FALSE | G21: https://github.com/freeCodeCamp/freeCodeCamp/pull/64535
B22: Merged 🎉 | C22: Warm-up | D22: Introducing Yourself Basics | E22: es-a1-warm-up-introducing-yourself-basics | F22: TRUE | G22: https://github.com/freeCodeCamp/freeCodeCamp/pull/62465
B23: Merged 🎉 | C23: Learn | D23: Meet Luna | E23: es-a1-learn-meet-luna | F23: TRUE | G23: https://github.com/freeCodeCamp/freeCodeCamp/pull/63825
B24: Merged 🎉 | C24: Learn | D24: Meet Mateo | E24: es-a1-learn-meet-mateo | F24: TRUE
B25: Merged 🎉 | C25: Learn | D25: Meet Julieta | E25: es-a1-learn-meet-julieta | F25: TRUE
B26: Merged 🎉 | C26: Practice | D26: Introducing Yourself Practice | E26: es-a1-practice-introducing-yourself | F26: TRUE | G26: https://github.com/freeCodeCamp/freeCodeCamp/pull/63985
B27: Merged 🎉 | C27: Review | D27: Introducing Yourself Review | E27: es-a1-review-introducing-yourself | F27: TRUE
B28: Merged 🎉 | C28: Quiz | D28: Introducing Yourself Quiz | E28: es-a1-quiz-introducing-yourself | F28: TRUE
B29: Estefania | C29: Module | D29: First Questions | E29: es-a1-module-first-questions | F29: FALSE | G29: https://github.com/freeCodeCamp/freeCodeCamp/pull/63672
B30: Merged 🎉 | C30: Warm-up | D30: First Questions Basics | E30: es-a1-warm-up-first-questions-basics | F30: TRUE
B31: Merged 🎉 | C31: Learn | D31: Meet Angela and Basti | E31: es-a1-learn-meet-angela-and-basti | F31: TRUE
B32: Merged 🎉 | C32: Practice | D32: First Questions Practice | E32: es-a1-practice-first-questions | F32: TRUE
B33: Merged 🎉 | C33: Review | D33: First Questions Review | E33: es-a1-review-first-questions | F33: TRUE
B34: Merged 🎉 | C34: Quiz | D34: First Questions Quiz | E34: es-a1-quiz-first-questions | F34: TRUE
B35: 3 | C35: Chapter | D35: Basic Personal Details | E35: es-a1-chapter-basic-personal-details | F35: FALSE
B36: Estefania | C36: Module | D36: Numbers 10 to 29 | E36: es-a1-module-numbers-10-to-29 | F36: FALSE | G36: https://github.com/freeCodeCamp/freeCodeCamp/pull/64080
B37: Merged 🎉 | C37: Warm-up | D37: Remember First Numbers | E37: es-a1-warm-up-remember-first-numbers | F37: TRUE
B38: Merged 🎉 | C38: Learn | D38: Numbers 10 to 29 | E38: es-a1-learn-numbers-10-to-29 | F38: TRUE
B39: Merged 🎉 | C39: Practice | D39: Using Numbers 10 to 29 | E39: es-a1-practice-using-numbers-10-to-29 | F39: TRUE
B40: Merged 🎉 | C40: Review | D40: Numbers 10 to 29 Review | E40: es-a1-review-numbers-10-to-29 | F40: TRUE
B41: Merged 🎉 | C41: Quiz | D41: Numbers 10 to 29 Quiz | E41: es-a1-quiz-numbers-10-to-29 | F41: TRUE
A42: 46038 | B42: Rafael | C42: Module | D42: Sharing Your Personal Details | E42: es-a1-module-sharing-your-personal-details | F42: FALSE
B43: Merged 🎉 | C43: Warm-up | D43: Getting Ready to Share Personal Details | E43: es-a1-warm-up-getting-ready-to-share-personal-details | F43: FALSE
B44: Merged 🎉 | C44: Learn | D44: Basic Personal Information | E44: es-a1-learn-basic-personal-information | F44: FALSE
B45: Merged 🎉 | C45: Learn | D45: Contact Information and Spelling | E45: es-a1-learn-contact-information-and-spelling | F45: FALSE
B46: Merged 🎉 | C46: Practice | D46: Personal Details in Action | E46: es-a1-practice-personal-details-in-action | F46: FALSE
B47: Merged 🎉 | C47: Review | D47: Sharing Your Personal Details Review | E47: es-a1-review-sharing-your-personal-details | F47: FALSE
B48: Merged 🎉 | C48: Quiz | D48: Sharing Your Personal Details Quiz | E48: es-a1-quiz-sharing-your-personal-details | F48: FALSE
B49: 4 | C49: Chapter | D49: Describing a Company and Its People | E49: es-a1-chapter-describing-company-and-people | F49: FALSE
A50: 46045 | B50: Estefania | C50: Module | D50: Numbers 30 to 100 | E50: es-a1-module-numbers-30-to-100 | F50: FALSE | G50: https://github.com/freeCodeCamp/freeCodeCamp/pull/65440
B51: Merged 🎉 | C51: Learn | D51: Numbers 30 to 60 | E51: es-a1-learn-numbers-30-to-60 | F51: FALSE
B52: Merged 🎉 | C52: Learn | D52: Numbers 61 to 100 | E52: es-a1-learn-numbers-61-to-100 | F52: FALSE
B53: Merged 🎉 | C53: Practice | D53: Using The First 100 Numbers | E53: es-a1-practice-using-the-first-100-numbers | F53: FALSE
B54: Merged 🎉 | C54: Review | D54: First 100 Numbers Review | E54: es-a1-review-first-100-numbers | F54: FALSE
B55: Merged 🎉 | C55: Quiz | D55: Numbers 30 to 100 Quiz | E55: es-a1-quiz-numbers-30-to-100 | F55: FALSE
B56: Rafael | C56: Module | D56: Describing a Company | E56: es-a1-module-describing-a-company | F56: FALSE
B57: Writing | C57: Warm-up | D57: Describing a Company Basics | E57: es-a1-warm-up-describing-a-company-basics | F57: FALSE
B58: Writing | C58: Learn | D58: What the Company Does | E58: es-a1-learn-what-the-company-does | F58: FALSE
B59: Waiting | C59: Practice | D59: What Departments Do | E59: es-a1-practice-what-departments-do | F59: FALSE
B60: Writing | C60: Learn | D60: Asking about a company | E60: es-a1-learn-asking-about-a-company | F60: FALSE
B61: Writing | C61: Practice | D61: Company profile | E61: es-a1-practice-company-profile | F61: FALSE
B62: Planning | C62: Review | D62: Talking About a Company | E62: es-a1-review-talking-about-a-company | F62: FALSE
B63: Planning | C63: Quiz | D63: Describing a Company Quiz | E63: es-a1-quiz-describing-a-company | F63: FALSE
B64: Estefania | C64: Module | D64: Describing People at Work | E64: es-a1-module-describing-people-at-work | G64: https://github.com/freeCodeCamp/freeCodeCamp/pull/65795
B65: To Review | C65: Warm-up | D65: Describing People at Work Basics | E65: es-a1-warm-up-describing-people-at-work-basics | F65: FALSE
B66: To Review | C66: Learn | D66: Mini Biographies | E66: es-a1-learn-mini-biographies | F66: FALSE
B67: To Review | C67: Learn | D67: Talking About Colleagues | E67: es-a1-learn-talking-about-colleagues | F67: FALSE
B68: To Review | C68: Practice | D68: Asking About Mini Biographies | E68: es-a1-practice-asking-about-mini-biographies | F68: FALSE
B69: To Review | C69: Learn | D69: Short Workplace Profile | E69: es-a1-learn-short-workplace-profile | F69: FALSE
B70: To Review | C70: Practice | D70: Asking About Short Workplace Profiles | E70: es-a1-practice-asking-about-short-workplace-profiles | F70: FALSE
B71: To Review | C71: Review | D71: Describing People at Work Review | E71: es-a1-review-describing-people-at-work | F71: FALSE
B72: To Review | C72: Quiz | D72: Describing People at Work | E72: es-a1-quiz-describing-people-at-work | F72: FALSE
B73: 5 | C73: Chapter | F73: FALSE
B74: Waiting | C74: Warm-up | F74: FALSE
B75: Waiting | C75: Learn | F75: FALSE
B76: Waiting | C76: Practice | F76: FALSE
B77: Waiting | C77: Learn | F77: FALSE
B78: Waiting | C78: Practice | F78: FALSE
B79: Waiting | C79: Review | F79: FALSE
B80: Waiting | C80: Quiz | F80: FALSE
F81: FALSE
F82: FALSE
F83: FALSE
F84: FALSE
F85: FALSE
F86: FALSE
F87: FALSE
F88: FALSE
F89: FALSE
F90: FALSE
F91: FALSE
F92: FALSE
... F110: FALSE

Sheet Basic Personal Details
A2: Chapter Basic Personal Details Objective
A3: By the end of this chapter, learners will be able to recognize, ask for, and provide personal information (such as name, surname, nationality, age, phone number, and email) using numbers 1–20 and the verbs llamarse, ser, and tener in the first and second person singular.
A4: Module 1 — Numbers from 10 to 29 Module 2 — Sharing Your Personal Details
A5: Module 1 | B5: ='Chapter Status'!D36 -> Numbers 10 to 29
A6: Listening By the end of this module, learners will be able to recognize numbers from 10 to 29 when spoken slowly in isolation or short sequences. By the end of this module, learners will be able to complete a listening task in which they write numbers in the order they hear them. Reading By the end of this module, learners will be able to match written numbers with their corresponding digits in a multiple-choice or matching exercise.
A7: Plan curricular Module 1
A8: Gramática | C8: Function | D8: Vocabulário Específico | E8: Nociones generales | F8: Nociones específicas
A9: Cardinal numbers 1–20 Review: tengo + number (for age) No new conjugations introduced | C9: Identifying and recognizing numbers Providing numerical information (age, phone digits) in controlled tasks Completing simple forms requiring numerical data | D9: números 0 to 29 | E9: Cantidad numérica: números cardinales Edad: número cardinal + “años” (input only) | F9: Datos personales: edad Datos personales: número de teléfono
A10: Tácticas y estrategias pragmáticas | C10: Géneros discursivos y productos textuales | D10: Ortografía | E10: Pronunciación y prosodia | F10: Cultura, saberes y comportamientos
A11: (None required — numbers are literal; no pragmatic strategies needed.) | C11: Formularios muy simples (personal data forms) Listas (numbers in order) | D11: Teach explicitly: Hyphen removal in compound numbers (dieciséis, diecisiete, etc.) Accent marks: dieciséis Lowercase number words in Spanish | E11: Teach explicitly: Stress patterns in numbers: diece-SÉIS, diecio-CHO Clear articulation of /s/ vs. /z/ depending on variety (neutral Latin American)
A12: Block type | B12: Block name | C12: Base Material | D12: Content planning | E12: Instructions/ notes
A13: ='Chapter Status'!C16 -> Warm-up | B13: ='Chapter Status'!D37 -> Remember First Numbers | C13: ES_A1_numbers-0-100 Review first numbers 0 to 9 Introduce other content if you judge necessary | E13: Objective is to review the first numbers to give a nice structure for the following blocks.
A14: ='Chapter Status'!C17 -> Learn | B14: ='Chapter Status'!D38 -> Numbers 10 to 29 | C14: Numbers 11 to 20 and any other audio you think is necessary ES_A1_numbers-0-100 numbers 10 to 29 | E14: Objectives: Recognize 11–20 when heard slowly Match written numbers to digits Identify 11–20 in simple tasks Content: Teach numbers 11–20 once, doce, trece, catorce, quince, dieciséis, diecisiete, dieciocho, diecinueve, veinte Highlight spelling patterns (Mention veintiún) Highlight accents where needed Orthographic point: dieciséis (accent)
A15: ='Chapter Status'!C18 -> Practice | B15: ='Chapter Status'!D39 -> Using Numbers 10 to 29 | C15: Numbers 1 to 20 and any other audio you think is necessary ES_A1_numbers-0-100 uno, dos, tres, cuatro, cinco, seis, siete, ocho, nueve, diez, once, doce, trece, catorce, quince, dieciséis, diecisiete, dieciocho, diecinueve, veinte | E15: Objectives: Consolidate recognition of 1–20 Write numbers correctly after listening Match, order, and identify numbers in various tasks Activities may include for example number ordering for example: Listening sequence: “Escribe el número según el orden en que lo escuchas.” Completing simple numeric fields (edad, número) No sentences longer than 2–3 words. Avoid introducing age grammar here.
A16: ='Chapter Status'!C19 -> Review | B16: ='Chapter Status'!D40 -> Numbers 10 to 29 Review | C16: Grammar Highlights Glossary | E16: Grammar Cardinal numbers 1–20 Accented forms: dieciséis No additional grammar Glossary Full list of numbers 1–20 in order Additional small glossary if necessary
A17: ='Chapter Status'!C20 -> Quiz | B17: ='Chapter Status'!D41 -> Numbers 10 to 29 Quiz | C17: Module Quiz | E17: The quiz block script requires either 10 or 20 questions. To pass, learners must score at least 90%. By default, our placeholder quiz block has 10 questions, but you can change it to 20 if you prefer.
A21: Module 2 - Sharing Your Personal Details
A22: Listening By the end of this module, learners will be able to recognize second-person questions about personal information (e.g., tu apellido, tu número, tu correo) when spoken slowly in short exchanges. By the end of this module, learners will be able to identify the personal information being requested in simple listening tasks (name, surname, nationality, age, phone number, email). Reading By the end of this module, learners will be able to match second-person prompts (e.g., tu nombre, tu nacionalidad) with the correct information fields on a simple personal data form. By the end of this module, learners will be able to understand short written prompts about personal data and choose correct first-person answers. Writing By the end of this module, learners will be able to complete a simple personal information form using first-person expressions (Me llamo…, Soy…, Tengo…, Mi correo es…, Mi número es…)
A23: Plan curricular Module 2
A24: Gramática | C24: Function | D24: Vocabulário Específico | E24: Nociones generales | F24: Nociones específicas
A25: 1. Second-person singular forms te llamas eres tienes (Chapter 2 showed these only inside questions; Module 2 teaches them as active forms learners can recognize and respond to.) 2. Possessive adjectives (essential for forms) mi tu 3. Email and number structures Mi número es… Mi correo es… Review only (NOT taught again) me llamo soy tengo Not included yet Él / Ella saved for Chapter 4 Su / sus saved for Chapter 4 | C25: Asking for personal information using tú. Giving personal information using yo. Completing personal data forms. Providing phone numbers and email addresses in simple formats. | D25: Key Vocabulary (Personal Data) Identity: nombre, apellido Age: edad Nationality & Country: nacionalidad, país, ciudad Profession: profesión Contact Info: correo electrónico, número de teléfono, móvil Other Data Words: formulario, datos personales Professions used in forms and profiles according to the monologues / dialogues: Contact terms: arroba (@), punto (.), número questions: Cuál | E25: dentidad personal (nombre, apellido) Datos de contacto (número, correo) Origen (nacionalidad, país) Edad (número + años) | F25: Datos personales nombre Datos personales apellido Datos personales nacionalidad Datos personales edad Datos personales profesión Datos personales correo, número
A26: Tácticas y estrategias pragmáticas | C26: Géneros discursivos y productos textuales | D26: Ortografía | E26: Pronunciación y prosodia | F26: Cultura, saberes y comportamientos
A27: Asking for clarification: ¿Tu apellido? ¿Tu número? Ellipsis: omitting tú in everyday questions ¿Cómo te llamas? (instead of ¿Cómo tú te llamas?) Confirming details: ¿Tu correo es…? | C27: Personal data forms (formularios) Brief personal profiles (profiles for HR) Mini onboarding dialogues | D27: Teach explicitly: (Review) Capitalization of names, surnames, countries, nationalities Accent marks: teléfono, número, país Email writing conventions: arroba, punto Review Gender adjustments for nationalities (colombiano/colombiana) | E27: Rhythm of phone numbers (pausing after 2–3 digits) Pronunciation of email components | F27: Personal data conventions in Latin America Optional: two-surname system (input only)
A28: Block type | B28: Block name | C28: Base Material | D28: Content planning | E28: Instructions/ notes
A29: ='Chapter Status'!C22 -> Warm-up | B29: ='Chapter Status'!D43 -> Getting Ready to Share Personal Details | C29: One audio with the alphabet suggested: ES_A1_alphabet.mp3 ES_A1_numbers-0-9 ES_A1_personal-details-vocabulary Nombre, apellido, Primer apellido, Segundo apellido, apodo, Nacionalidad, Profesión, Correo electrónico, Número de teléfono | D29: Write your planning for this block here. Check the the Curricular plan below to check what's expected from this module. Do the same to the following rows | E29: Activate prior knowledge from Chapter 1 (alphabet) and Module 1 (numbers 1–10). Present a short vocabulary list with personal data terms that will appear in the Learn blocks. Do not introduce new grammar. Keep exposure brief and focused.
A30: ='Chapter Status'!C23 -> Learn | B30: ='Chapter Status'!D44 -> Basic Personal Information | C30: ES_A1_esteban-personal-records-dialogue-with-angela Intro (Not to record) Esteban visits the Human Resources office at Andes Commerce to update his personal information for the company records. Ángela, the HR representative, asks him basic questions to complete the form. Dialogue (to record) Ángela: Hola, buenas tardes. Gracias por venir. ¿Cuál es tu nombre y apellido? Esteban: Me llamo Esteban Navarro Huamán. Ángela: ¿Navarro con dos erres? Esteban: Sí, con dos erres. Ángela: ¿Y Huamán? ¿Cómo se escribe? Esteban: H-U-A-M-A-N, con acento en la última a. Ángela: Perfecto. Entonces, Esteban Navarro Huamán. ¿Cuál es tu nacionalidad? Esteban: Soy peruano. Ángela: Ah, de Perú. Muy bien. ¿Y tu profesión? Esteban: Soy desarrollador web. Ángela: Gracias, Esteban. Todo listo por hoy. Esteban: Gracias, Ángela. Hasta luego. ES_A1_mateo-email-dialogue-with-camila Camila: Hola, Mateo. ¿Cuál es tu correo electrónico? Mateo: Mi correo es mateo.delgado@sanjuan.pr. ¿Quieres que te lo deletree? Camila: Sí, por favor. Mateo: Es m - a - t - e - o punto d - e - l - g - a - d - o arroba s - a - n - j - u - a - n punto p - r. Camila: ¿sanjuan.pr? Mateo: Sí, correcto. Camila: Perfecto. Muchas gracias. Mateo: ¡De nada! | D30: Description: --Esteban visits the Human Resources office at Andes Commerce to update his personal information for the company records. Ángela, the HR representative, asks him basic questions to complete the form.-- | E30: Dialogue ES_A1_esteban-angela-update-personal-records is perfect to introduce vocab numbre and apellido, review alphabet (chapter 1), content from chapter 2 and some particular cases as double erres. If a sentence is new (like todo listo por hoy) make sure to teach it. Make sure to explain questions starting with Cuál, and similar questions where Cuál is omited but the meaning is there. You chould also teach the word "Como". Make sure to teach key vocab related to email and phone numbers as "te lo deletree" and so on. ES_A1_contact-info-dialogue-camila-mateo is perfect to reinforce spelling while introducing numbers, and sentences to confirm information. Take your time with these number tasks. Grammar wise, remember that this module introduces much of the conjugation of Tú, while review Yo. But the main focus is second person. This block has to be planned alongside the following learn block
A31: Learn | B31: ='Chapter Status'!D45 -> Contact Information and Spelling | C31: ES_A1_mateo-camila-phone-number-dialogue Mateo: Hola, Camila. ¿Cuál es tu número de teléfono? Camila: Mi número es +57 313 445 9280. Mateo: ¿Puedes repetirlo? Camila: Claro, es +57 313 445 9280. Mateo: Gracias. Camila: ¿Y el tuyo, Mateo? Mateo: Es 213 554 0028. Camila: ¿Otra vez, por favor? Mateo: 213 554 0028. ES_A1_basti-personal-details Intro (not to record) Basti is on a call confirming his personal details. In this audio you listen to his side of the conversation. To record Hola, buenas noches. Me llamo Sebastián Ávila Gómez. Sebastián se escribe s-e-b-a-s-t-i-á-n, con acento en la última a. ¿Puedo usar mi apodo? Mi apodo es Basti. Se escribe B-a-s-t-i. Sí, Gómez termina en z. Soy guatemalteco y soy analista junior. Mi correo completo es basti.ag@quetzal.gt El usuario es b-a-s-t-i punto a-g. El dominio es q-u-e-t-z-a-l punto g-t. Y mi número es +502 4489 2201. Sí, correcto. Gracias. | E31: ES_A1_basti-personal-details continues from the previous learn block, I've only separated it to avoid making the first learn block too long. make sure to plan this together with the previous block.
A32: ='Chapter Status'!C26 -> Practice | B32: ='Chapter Status'!D46 -> Personal Details in Action | C32: ES_A1_personal-details-just-questions ¿Cuál es tu nombre?; ¿Cuál es tu apellido?; ¿Cuál es tu primer apellido?; ¿Cuál es tu segundo apellido?; ¿Cuál es tu nombre y apellido?; ¿Cuál es tu apodo?; ¿Cuál es tu nacionalidad?; ¿Cuál es tu profesion?; ¿Cuál es tu número de teléfono?; ¿Cuál es tu correo electrónico? ¿Cómo se escribe? ¿Cómo te llamas? ¿Cómo se deletrea? ¿Quieres que te lo deletree? ¿ Puedes repetirlo, por favor?, ¿ Puedes repetirlo? ¿Otra vez, por favor? ES_A1_all-special-characters ES_A1_julieta-personal-details Intro (not to record) Julieta is in a call confirming his personal details. In this audio you listen to her side of the conversation. To record Hola, sí, buenos días. Me llamo Julieta Cáceres López. Cáceres lleva acento en la primera a. López también tiene acento en la o , y termina en z. Mi correo es julieta.caceres@andes.com. Repito: j-u-l-i-e-t-a punto c-a-c-e-r-e-s arroba a-n-d-e-s punto com. Sí, correcto. Soy uruguaya y soy estratega de marketing. Y mi número es +598 94 227 495. Sí, ese mismo. De acuerdo, perfecto. Muchas gracias. Hasta luego. Reading practice Formulario de datos personales ES_A1_luna-personal-data-form Nombre: Luna Primer apellido: Méndez Segundo apellido: Pérez Nacionalidad: chilena Profesión: científica de datos Correo electrónico: luna.mendez@andes.com Número de teléfono: +56 923 881 240 Edad: 25 | E32: I wasn't sure how you two would like to proceed with the practice block, so I've prepared some audio with questions. A text from Julieta using the same structure as Basti and a profile form from Luna. Feel free to explore how you can use these in practice. For example, you could combine ES_A1_luna-personal-data-form text wit some questions from ES_A1_personal-details-just-questions, and ask learner to find the information the audio is asking on the form. There are endless possibilities here. =)
A33: ='Chapter Status'!C27 -> Review | B33: ='Chapter Status'!D47 -> Sharing Your Personal Details Review | C33: Grammar Highlights Glossary
A34: ='Chapter Status'!C28 -> Quiz | B34: ='Chapter Status'!D48 -> Sharing Your Personal Details Quiz | C34: Module Quiz | E34: The quiz block script requires either 10 or 20 questions. To pass, learners must score at least 90%. By default, our placeholder quiz block has 10 questions, but you can change it to 20 if you prefer.

Sheet Spanish Fundamentals
A2: Chapter Spanish Fundamentals Objective
A3: By the end of this Chapter, learners will be able to identify and differentiate spanish Alphabet letters
A4: List the modules inside the chapter here
A5: Module 1 The alphabet, accents, and punctuation
A6: - Vowels: By the end of this module learners will be able to identify the five vowels in spanish and differentiate their sounds. - Consonants: By the end of this module learners will be able to identify the consonants and differentiate their sounds. - Consonants: By the end of the module, learners will be able to type special ñ - Punctuation: By the end of this module, learners will be able to correctly type the opening of signo de interrogación and signo de exclamación ¿? ¡!
A7: Plan curricular Module 1
A8: Gramática | C8: Function | D8: Vocabulário Específico | E8: Nociones generales | F8: Nociones específicas
A9: List of grammar to focus on this lesson | C9: list of functions to be covered | D9: List of specific vocab | E9: List here the general field you are teaching based on the reference material | F9: List here the specific notions you are teaching based on the reference material
A10: Tácticas y estrategias pragmáticas | C10: Géneros discursivos y productos textuales | D10: Ortografía | E10: Pronunciación y prosodia | F10: Cultura, saberes y comportamientos
A11: If you are not covering this topic leave it empty | C11: If you are teaching writing you should pay extra attentio to this section. If you are not covering this topic leave it empty | D11: If you are teaching ortography list it here. If not leave it empty | E11: If you are teaching pronunciation list it here. If not leave it empty | F11: If you are not covering this topic leave it empty
A12: Block type | B12: Block name | C12: Base Material | D12: Content planning | E12: Instructions/ notes
A13: ='Chapter Status'!C7 -> Learn | B13: ='Chapter Status'!D7 -> Vowels | D13: Write your planning for this block here. Check the the Curricular plan below to check what's expected from this module. Do the same to the following rows | E13: Make sure you have audio needed on the CDN (Or that you'll record them)
A14: ='Chapter Status'!C8 -> Learn | B14: ='Chapter Status'!D8 -> Consonants and Special Characters | C14: There can be more than one Learn block. It will depend on how long and complex is your base material. Paste the base material (dialogue or monologue) to be covered in this learning section | E14: Make sure you have audio needed on the CDN (Or that you'll record them)
A15: Learn | B15: ='Chapter Status'!D10 -> The First Ten Numbers | C15: Numbers 0 to 10 and any other audio you think is necessary ES_A1_numbers-0-100 zero, uno, dos, tres, cuatro, cinco, seis, siete, ocho, nueve, diez | D15: Write your planning for this block here. Check the the Curricular plan below to check what's expected from this module. Do the same to the following rows | E15: Objectives: Recognize 1–10 when heard slowly Match written numbers to digits Identify numbers Content: Teach numbers 1–10 individually uno, dos, tres, cuatro, cinco, seis, siete, ocho, nueve, diez Each number is taught with: written form digit form a simple example sentence (optional, single-word preferred) No inflection, no gender No verb instruction
A16: Learn | B16: ='Chapter Status'!D11 -> The First Ten Numbers Practice
A17: ='Chapter Status'!C12 -> Review | B17: ='Chapter Status'!D12 -> Spanish Fundamentals Review | C17: Grammar Highlights Glossary
A18: ='Chapter Status'!C13 -> Quiz | B18: ='Chapter Status'!D13 -> Spanish Fundamentals Quiz | C18: Module Quiz | E18: The quiz block script requires either 10 or 20 questions. To pass, learners must score at least 90%. By default, our placeholder quiz block has 10 questions, but you can change it to 20 if you prefer.

Sheet Greetings and Introductions
A2: Chapter Greetings and Introductions Objective
A3: By the end of this Chapter, learners will be able to greet others, introduce themselves, and exchange basic personal information (such as name, nationality, and where they are from) using simple expressions in Spanish.
A4: Module 1: Greetings and farewells (Hola, buenos días, adiós…) Module 2: Introducing yourself (Me llamo…, Soy de…, Tengo … años) Module 3: Asking and giving basic personal information (¿Cómo te llamas?, ¿De dónde eres?, ¿Qué haces?)
A5: Module 1 Greetings and Farewells
A6: "By the end of this module, learners will be able to greet others, introduce themselves with name and profession, and say goodbye using simple expressions in Spanish. Listening By the end of the module, learners will be able to identify common greetings, introductions (Me llamo… / Soy…), and farewells when spoken slowly in short monologues. Reading By the end of the module, learners will be able to match 5 greetings and farewells with their English meanings in a multiple-choice or matching exercise. Writing By the end of the module, learners will be able to complete a short self-introduction text (monologue) with missing words, choosing correctly from a provided word list (including distractors)."
A7: Plan curricular Module 1
A8: Gramática | C8: Function | D8: Vocabulário Específico | E8: Nociones generales | F8: Nociones específicas
A9: "Grammar to cover explicitly in Module 1 Names without article: Soy Elena. Me llamo Camila. Time of day nouns (greetings): Buenos días. Buenas tardes. Buenas noches. Verb ser (present, 1st person singular): Soy Camila. Soy analista. Simple affirmative sentences: Me llamo Esteban. Soy diseñadora. Grammar present but not taught yet (exposure only) Gender of nouns (-o / -a): diseñador / diseñadora Use and omission of the article: Soy diseñadora Subject pronouns and omission: Soy Elena (without yo)" | C9: "Identificar Dar información (datos personales: nombre, profesión) Expresar certeza (con enunciados declarativos)" | D9: Diseñadora, analista, desarrollador | E9: "Cualidad general: ser - Soy Camila. Soy analista. Referencias generales de nociones temporales: día, tarde, noche, mañana, pronto" | F9: "Datos personales: Nombre (nombre, apellido, llamarse) Datos personales: Profesión (Soy analista, Soy diseñadora, Soy desarrollador) Profesiones y cargos (basic jobs)"
A10: Tácticas y estrategias pragmáticas | C10: Géneros discursivos y productos textuales | D10: Ortografía | E10: Pronunciación y prosodia | F10: Cultura, saberes y comportamientos
A11: Mantenimiento del referente e hilo discursivo: Sustitución por Ø (subject ellipsis in Soy Elena instead of Yo soy Elena) | C11: Notas muy breves y sencillas (escritas) | D11: Teach explicitly: Capitalization at the beginning of sentences. Capitalization of names. Expose only: Accent marks (días, adiós). ll in llamo. | E11: Not covered | F11: not covered
A12: Block type | B12: Block name | C12: Base Material | D12: Content planning | E12: Instructions/ notes
A13: ='Chapter Status'!C16 -> Warm-up | B13: ='Chapter Status'!D16 -> Greetings and Farewells Basics | C13: Greetings Hola – Hello Buenos días – Good morning Buenas tardes – Good afternoon Buenas noches – Good evening / Good night Introductions Me llamo… – My name is… Soy… – I am… Professions diseñadora, analista, desarrollador Farewells Adiós – Goodbye chao – Bye Hasta luego – See you later Hasta mañana – See you tomorrow Hasta pronto – See you soon | D13: Write your planning for this block here. Check the the Curricular plan below to check what's expected from this module | E13: Make sure you have audio needed on the CDN (Or that you'll record them)
A14: ='Chapter Status'!C17 -> Learn | B14: ='Chapter Status'!D17 -> Greetings During the Day | C14: Lesson 1 Monologues with Professions Monologue 1 Morning Hola, buenos días. Me llamo Elena. Soy diseñadora. Hasta luego. Adiós. Monologue 2 Afternoon Hola, buenas tardes. Soy Camila. Soy analista. Adiós. Hasta pronto. Monologue 3 Night Hola, buenas noches. Me llamo Esteban. Soy desarrollador. Hasta mañana. Chao. | D14: Write your planning for this block here. Check the the Curricular plan below to check what's expected from this module | E14: Make sure you have audio needed on the CDN (Or that you'll record them)
A15: ='Chapter Status'!C18 -> Practice | B15: ='Chapter Status'!D18 -> Greetings and Farewells Practice | C15: All 3 monologues and Writing Practice Camila is introducing herself at work in the afternoon. Complete her introduction with the correct words. ___, buenas ___. ___ Camila. ___ analista. Hasta ___, ___. Word options (with distractors) : Hola – Me llamo – Soy – Adiós – luego – mañana – noches – pronto Correct answer: Writing practice 1 Hola, buenas tardes. Me llamo Camila. Soy analista. Hasta luego, Adiós. | D15: Write your planning for this block here. Check the the Curricular plan below to check what's expected from this module | E15: Make sure to also include speaking tasks even if we still don't have them available.
A16: ='Chapter Status'!C19 -> Review | B16: ='Chapter Status'!D19 -> Greetings and Farewells Review | C16: Grammar Highlights Glossary | D16: Write your planning for this block here. Check the the Curricular plan below to check what's expected from this module
A17: ='Chapter Status'!C20 -> Quiz | B17: ='Chapter Status'!D20 -> Greetings and Farewells Quiz | C17: Module Quiz | D17: Write your planning for this block here. Check the the Curricular plan below to check what's expected from this module | E17: The quiz block script requires either 10 or 20 questions. To pass, learners must score at least 90%. By default, our placeholder quiz block has 10 questions, but you can change it to 20 if you prefer.
A21: Module 2 – Introducing Yourself Objectives RAFAEL
A22: "Main Objective By the end of this module, learners will be able to introduce themselves with name, profession, nationality, and age using simple expressions in Spanish. Listening By the end of the Module, learners will be able to identify introductions that include name, profession, nationality, and age when spoken slowly in short monologues. Reading By the end of the module, learners will be able to match written sentences of self-introduction (name, profession, nationality, age) with their English meanings in a multiple-choice or matching exercise. Writing By the end of the module, learners will be able to complete a short self-introduction text (monologue) with missing words (name, profession, nationality, age) by selecting the correct items from a word list (including distractors)."
A23: Plan curricular Module 2 - Rafael
A24: Gramática | C24: Function | D24: Vocabulário Específico | E24: Nociones generales | F24: Nociones específicas
A25: Grammar to cover explicitly ser with profession and nationality. tener with numbers to express age. Simple affirmative sentences (SVO order). Subject–attribute agreement (chileno/chilena, uruguayo/uruguaya). Numbers (cardinals for age). Grammar present but not taught yet (exposure only) Género en nacionalidades (chileno/chilena, puertorriqueño/puertorriqueña) Plural de años (Tengo 28 años → plural not explained) | C25: Identificar: nombre, profesión, nacionalidad Dar información: datos personales (edad, nacionalidad) Expresar certeza: enunciados declarativos | D25: Científica de datos – Data Scientist Ingeniero de software – Software Engineer Estratega de marketing – Marketing Strategist | E25: Profesion: ser + profesion Example: Soy Ingeniero de Software. Soy cientifica de datos. Origen: ser + nacionalidad Example: Soy chilena. Soy uruguaya. Edad, vejez: tener + número cardinal ~ años Example: Tengo 28 años. Cantidad numérica: números cardinales Example: veinticinco, treinta, treinta y seis | F25: Datos personales: nombre Datos personales: profesión Datos personales: nacionalidad Datos personales: edad
A26: Tácticas y estrategias pragmáticas | C26: Géneros discursivos y productos textuales | D26: Ortografía | E26: Pronunciación y prosodia | F26: Cultura, saberes y comportamientos
A27: Mantenimiento del referente e hilo discursivo: Sustitución por Ø (Soy chilena instead of Yo soy chilena) | C27: Conversaciones cara a cara, muy breves e informales, sobre personas (adapted here as short monologues of self-introduction) | D27: Ortografía to cover explicitly in Module 2 Mayúscula en nombres y nacionalidades (Luna, Chilena, Uruguaya, Puertorriqueño) Uso de tilde en palabras comunes (años, científica, puertorriqueño) | E27: Not covered | F27: Not covered
A28: Block type | B28: Block name | C28: Base Material | D28: Content planning | E28: Instructions
A29: ='Chapter Status'!C22 -> Warm-up | B29: ='Chapter Status'!D22 -> Introducing Yourself Basics | C29: Professions Científica de datos Ingeniero de software Estratega de marketing Nationalities chilena puertorriqueño uruguaya Numbers (for age) veinte – twenty veinticinco – twenty-five veintiocho – twenty-eight treinta – thirty treinta y seis – thirty-six | D29: Warm-up (multiple choice tasks) Profession - Científica de datos - Ingeniero de software - Estratega de marketing Nationality - Chilena - Puertorriqueño - Uruguaya Number (age) - 28 años - 25 años - 36 años
A30: ='Chapter Status'!C23 -> Learn | B30: ='Chapter Status'!D23 -> Meet Luna | C30: Meet Luna Hola, buenos días. Me llamo Luna. Soy científica de datos. Soy chilena. Tengo veintiocho años. Hasta luego. Adiós. | D30: Warm-up (multiple choice tasks) Using `ser` + profession - Soy cientifica de datos Using `ser` + nationality - Soy Chilena Using `tener` + number (age) - Tengo 28 años
A31: ='Chapter Status'!C24 -> Learn | B31: ='Chapter Status'!D24 -> Meet Mateo | C31: Meet Mateo Hola, buenas tardes. Soy Mateo. Soy ingeniero de software. Soy puertorriqueño. Tengo veinticinco años. Adiós. Hasta pronto. | D31: Warm-up (multiple choice tasks) Using `ser` + profession - Soy ingeniero de software Using `ser` + nationality - Soy puertorriqueño Using `tener` + number (age) - Tengo 25 años
A32: ='Chapter Status'!C25 -> Learn | B32: ='Chapter Status'!D25 -> Meet Julieta | C32: Meet Julieta Hola, buenas noches. Chile Soy uruguaya. Tengo treinta y seis años. Hasta mañana. Chau." | D32: Warm-up (multiple choice tasks) Using `ser` + profession - Soy estratega de marketing Using `ser` + nationality - Soy uruguaya Using `tener` + number (age) - Tengo 36 años
A33: ='Chapter Status'!C26 -> Practice | B33: ='Chapter Status'!D26 -> Introducing Yourself Practice | C33: All 3 monologues and mateo_intro_practice Hola, buenas BLANK. Me llamo Mateo. Soy BLANK de software. Soy BLANK. BLANK veinticinco años. Word options: noches, ingeniero – tardes – estratega – tengo - soy – colombiana - puertorriqueño Correct answer: Hola, buenas noches. Me llamo Mateo. Soy ingeniero de software. Soy puertorriqueño. Tengo veinticinco años. | D33: Practice (fill blanks, true and false, and multiple choice tasks) Using | E33: Make sure to also include speaking tasks even if we still don't have them available.
A34: ='Chapter Status'!C27 -> Review | B34: ='Chapter Status'!D27 -> Introducing Yourself Review | C34: Grammar Highlights Glossary | D34: Write your planning for this block here. Check the the Curricular plan below to check what's expected from this module
A35: ='Chapter Status'!C28 -> Quiz | B35: ='Chapter Status'!D28 -> Introducing Yourself Quiz | C35: Module Quiz | D35: Write your planning for this block here. Check the the Curricular plan below to check what's expected from this module | E35: The quiz block script requires either 10 or 20 questions. To pass, learners must score at least 90%. By default, our placeholder quiz block has 10 questions, but you can change it to 20 if you prefer.
A38: Module 3 – First Questions
A39: "Main Objective By the end of this module, learners will be able to ask and answer basic questions about name, profession, nationality, and age using simple expressions in Spanish. Listening By the end of the module, learners will be able to recognize common informal questions about personal information (name, origin, profession, age) and identify their meaning when spoken slowly in a short dialogue. Reading By the end of the module, learners will be able to match written questions about personal information with their English equivalents in a multiple-choice or matching exercise. Writing By the end of the module, learners will be able to complete a short dialogue with missing questions or answers by selecting the correct items from a provided word list with distractors."
A40: Plan curricular Module 3
A41: Gramática | C41: Function | D41: Vocabulário Específico | E41: Nociones generales | F41: Nociones específicas
A42: Interrogative pronouns and adverbs ¿Cómo…? (¿Cómo te llamas?) ¿De dónde…? (¿De dónde eres?) ¿Qué…? (¿Qué haces?) ¿Cuántos…? (¿Cuántos años tienes?) Verb ser (present tense) Soy, eres (for identity, origin, nationality, profession). Verb tener (present tense, age expression) Tengo … años. Subject ellipsis (Ø) Soy Basti. Soy de Guatemala. (instead of Yo soy Basti). Declarative sentences (simple) Me llamo Ángela. Soy representante de recursos humanos. Question word order ¿Cómo te llamas? (interrogative first, verb second). | C42: Pedir información: datos personales (nombre, origen, nacionalidad, edad, profesión) Dar información: datos personales (nombre, origen, nacionalidad, edad, profesión) Identificar (nombre, profesión, nacionalidad) Expresar certeza (enunciados declarativos) | D42: representante de recursos humanos, analista junior | E42: Origen: ser de + país/ciudad Nacionalidad: ser + nacionalidad Edad: tener + número cardinal + años Cantidad numérica: números cardinales Cualidad general: ser (identidad, profesión) | F42: Datos personales: nombre Datos personales: profesión Datos personales: nacionalidad Datos personales: edad Datos personales: lugar de origen
A43: Tácticas y estrategias pragmáticas | C43: Géneros discursivos y productos textuales | D43: Ortografía | E43: Pronunciación y prosodia | F43: Cultura, saberes y comportamientos
A44: Mantenimiento del referente e hilo discursivo: Sustitución por Ø (Soy guatemalteco instead of Yo soy guatemalteco) Estrategias de reciprocidad: uso de “¿Y tú?” para mantener la interacción | C44: Conversaciones cara a cara, muy breves e informales, sobre personas | D44: Mayúscula en nombres, países y nacionalidades (Ángela, Guatemala, Guatemalteco, El Salvador, Salvadoreña) Uso de tilde en palabras comunes (años, también, Ángela) Signos de interrogación al inicio y final de las preguntas (¿Cómo te llamas?) | E44: Not covered | F44: Not covered
A45: Block type | B45: Block name | C45: Base Material | D45: Content planning | E45: Instructions/ notes
A46: ='Chapter Status'!C30 -> Warm-up | B46: ='Chapter Status'!D30 -> First Questions Basics | C46: Questions (informal) ¿Cómo? ¿De dónde? ¿A qué? – ¿Cuántos? Mucho gusto – Nice to meet you Encantado/a – Pleased to meet you Igualmente – Likewise Profesiones: representante de recursos humanos, analista junior Nacionalidades: salvadoreña, guatemalteco Países: El Salvador, Guatemala | D46: Write your planning for this block here. Check the the Curricular plan below to check what's expected from this module | E46: Make sure you have audio needed on the CDN (Or that you'll record them)
A47: ='Chapter Status'!C31 -> Learn | B47: ='Chapter Status'!D31 -> Meet Angela and Basti | C47: Meet Ángela and Basti Ángela: Hola, buenas tardes. ¿Cómo te llamas? Basti: Mi nombre es Sebastián. Me llaman Basti. ¿Y tú? Ángela: Me llamo Ángela. Basti: Mucho gusto, Ángela. ¿De dónde eres? Ángela: Soy de El Salvador. Soy salvadoreña. ¿Y vós? Basti: Soy de Guatemala. Soy guatemalteco. Ángela: ¿Cuántos años tienes? Basti: Tengo 21 años. ¿Y tú? Ángela: Tengo 35 años. Basti: ¿A qué te dedicas, Ángela? Ángela: Soy representante de recursos humanos. ¿Y vós? Basti: Soy analista junior. Ángela: Encantada de conocerte, Basti. Basti: Igualmente. | D47: Write your planning for this block here. Check the the Curricular plan below to check what's expected from this module | E47: Make sure you have audio needed on the CDN (Or that you'll record them)
A48: ='Chapter Status'!C32 -> Practice | B48: ='Chapter Status'!D32 -> First Questions Practice | C48: Writing Camila: Hola, buenas tardes. ___ Mateo: Me llamo Mateo. ¿Y tú? Camila: Me llamo Camila. Mateo: Mucho gusto. ___ Camila: Soy de Colômbia. Soy ___. ¿Y tú? Mateo: Soy de _. Soy puertorriqueño. Camila: ___ Mateo: Soy ingeniero de software. ¿Y tú? Camila: Soy analista de datos. Camila: ___ Mateo: Tengo 25 años. ¿Y tú? Camila: Tengo 30 años. Word options: ¿Cómo te llamas? – ¿De dónde eres? – ¿Qué haces? – ¿Cuántos años tienes? – Colombia – colombiana – Puerto Rico ¿Dónde vives? – ¿Trabajas aquí? – Puerto Rico – uruguaya Correct answer: Lesson 3 writing practice 1 Camila: Hola, buenas tardes. ¿Cómo te llamas? Mateo: Mi nombre es Mateo. ¿Y tú? Camila: Me llamo Camila. Mateo: Mucho gusto. ¿De dónde eres? Camila: Soy de Colombia. Soy colombiana. ¿Y tú? Mateo: Soy de Puerto Rico. Soy puertorriqueño. Camila: ¿A qué te dedicas? Mateo: Soy ingeniero de software. ¿Y tú, Camila? Camila: Soy analista de datos. ¿Cuántos años tienes? Mateo: Tengo 25 años. ¿Y tú? Camila: Tengo 30 años. | D48: Florencia: Hola, buenas tardes. Mi nombre es Florencia. ¿Cómo te llamas? Federico: Mi nombre es Federico. ¿De dónde eres? Florencia: Soy de El Salvador. ¿Y tú? Federico: Soy de Argentina. Florencia: ¿Cuántos años tienes? Federico: Tengo treinta y seis años. ¿Y tú? Florencia: Tengo treinta y cinco años. Encantada de conocerte, Federico. Federico: Igualmente. | E48: Make sure to also include speaking tasks even if we still don't have them available.
A49: ='Chapter Status'!C33 -> Review | B49: ='Chapter Status'!D33 -> First Questions Review | D49: Write your planning for this block here. Check the the Curricular plan below to check what's expected from this module
A50: ='Chapter Status'!C34 -> Quiz | B50: ='Chapter Status'!D34 -> First Questions Quiz | D50: Write your planning for this block here. Check the the Curricular plan below to check what's expected from this module | E50: The quiz block script requires either 10 or 20 questions. To pass, learners must score at least 90%. By default, our placeholder quiz block has 10 questions, but you can change it to 20 if you prefer.

Sheet Describing a Company and Its Pe
A2: Chapter Describing a Company and Its People
A3: By the end of this chapter, learners will be able to describe basic information about a company and its employees using simple third-person forms (“él / ella” and “la empresa / el equipo”). They will identify and use numbers from 0 to 100, recognize workplace department names, and read or complete short third-person descriptions related to a company context.
A4: Module 1 — Numbers from 30 to 100 Module 2 — Describing a company Module 3 - Describing people at work
A5: Module 1 Numbers from 30 to 100
A6: Listening Objectives By the end of this module, learners will be able to identify numbers between 30 and 100 when spoken at a slow pace in short audio clips. By the end of this module, learners will be able to recognize quantities expressed with numbers 30–100 in simple recorded statements. Reading Objectives By the end of this module, learners will be able to match written numbers (30–100) to their digit forms. Writing Objectives By the end of this module, learners will be able to write numbers from 30 to 100 in words in short, controlled tasks.
A7: Plan curricular Module 1
A8: Gramática | C8: Function | D8: Vocabulário Específico | E8: Nociones generales | F8: Nociones específicas
A9: Cardinal numbers from 30 to 100 Compound number structure: tens + y + unit treinta y uno, cuarenta y cinco, sesenta y ocho Round numbers: treinta, cuarenta, cincuenta, sesenta, setenta, ochenta, noventa, cien No new verb conjugations introduced | C9: Identifying and recognizing numbers from 30 to 100 in spoken form Matching written numbers with numerical values Expressing quantities using numbers in controlled contexts Completing simple informational statements with numbers | D9: List of specific vocab | E9: Cantidad numérica: números cardinales | F9: List here the specific notions you are teaching based on the reference material
A10: Tácticas y estrategias pragmáticas | C10: Géneros discursivos y productos textuales | D10: Ortografía | E10: Pronunciación y prosodia | F10: Cultura, saberes y comportamientos
A11: If you are not covering this topic leave it empty | C11: If you are teaching writing you should pay extra attentio to this section. If you are not covering this topic leave it empty | D11: If you are teaching ortography list it here. If not leave it empty | E11: If you are teaching pronunciation list it here. If not leave it empty | F11: If you are not covering this topic leave it empty
A12: Block type | B12: Block name | C12: Base Material | D12: Content planning | E12: Instructions/ notes
A13: ='Chapter Status'!C51 -> Learn | B13: ='Chapter Status'!D51 -> Numbers 30 to 60 | C13: Numbers 30 to 100 and any other audio you think is necessary ES_A1_describing_company_and_people_numbers_21_100 (Already created) | D13: Write your planning for this block here. Check the the Curricular plan below to check what's expected from this module. Do the same to the following rows | E13: Objectives: Recognize numbers from 30 to 100 when heard slowly Match written numbers to digits Identify numbers Each number is taught with: written form digit form a simple example sentence (optional, single-word preferred) No inflection, no gender No verb instruction
A14: ='Chapter Status'!C53 -> Practice | B14: ='Chapter Status'!D53 -> Using The First 100 Numbers | C14: Here you'll probably use all the base material from your learn blocks. If you want you can create more audios to support the lesson | E14: Make sure to also include speaking tasks even if we still don't have them available.
A15: ='Chapter Status'!C54 -> Review | B15: ='Chapter Status'!D54 -> First 100 Numbers Review | C15: Grammar Highlights Glossary
A16: ='Chapter Status'!C55 -> Quiz | B16: ='Chapter Status'!D55 -> Numbers 30 to 100 Quiz | C16: Module Quiz | E16: The quiz block script requires either 10 or 20 questions. To pass, learners must score at least 90%. By default, our placeholder quiz block has 10 questions, but you can change it to 20 if you prefer.
A20: Module 2 Describing a Company
A21: Listening Objectives By the end of this module, learners will be able to identify basic information about a company (name, website, location, number of employees, departments) in short spoken statements. By the end of this module, learners will be able to recognize descriptions of a company using third-person forms such as se llama, es, tiene. Reading Objectives By the end of this module, learners will be able to read and extract key details from short third-person texts about a company. By the end of this module, learners will be able to match department names to short descriptions in a company context. By the end of this module, learners will be able to identify numbers 31–100 inside short workplace descriptions (tiene cincuenta empleados, veintidós oficinas). Writing Objectives By the end of this module, learners will be able to complete short third-person statements about a company using a guided word bank (e.g., La empresa se llama… / Tiene… empleados.).
A22: Plan curricular Module 2 - Rafa
A23: Gramática | C23: Function | D23: Vocabulário Específico | E23: Nociones generales | F23: Nociones específicas
A24: Presente de indicativo en 3.ª persona singular: ser (es), llamarse (se llama), tener (tiene), estar (está) Estructura básica SN + verbo en tercera persona (La empresa es…, La empresa tiene…) Uso de artículos definidos con sustantivos de empresa y departamentos (la empresa, el departamento de…) Números cardinales 31–100 en contexto informativo (setenta y tres empleados) | C24: Pedir información básica sobre una empresa (¿Cómo se llama…?, ¿Dónde está…?, ¿Cuántos empleados tiene…?, ¿Cuál es el sitio web?) Dar información básica sobre una empresa (Es una empresa de…, Tiene…, Está en…) Identificar y describir una empresa y sus departamentos | D24: Empresa y sector: empresa empresa de tecnología sector Estructura organizativa: departamento empleados Departamentos: ingeniería datos y analítica producto y gestión de proyectos diseño y experiencia de usuario marketing control de calidad personas / recursos humanos aprendizaje y desarrollo Información corporativa: sede sitio web Números: | E24: Identidad identificación de entidades (empresa) Cantidad número de empleados Espacio / localización ciudad y país (sede) Existencia y posesión presencia de departamentos y empleados | F24: Nociones específicas Ámbito profesional y laboral empresa tecnológica estructura básica de una empresa Organización interna departamentos y funciones Contexto digital sitio web corporativo
A25: Tácticas y estrategias pragmáticas | C25: Géneros discursivos y productos textuales | D25: Ortografía | E25: Pronunciación y prosodia | F25: Cultura, saberes y comportamientos
A26: If you are not covering this topic leave it empty | C26: Géneros discursivos y productos textuales Conversación breve cara a cara (preguntas y respuestas sobre trabajo) Diálogo informativo (entre compañeros de trabajo) Descripción informativa breve de una empresa Ficha / perfil de empresa con datos básicos | D26: tecnología sector Estructura ingeniería proyectos (Not projectos) aprendizaje y desarrollo | E26: Ingenería gestión | F26: If you are not covering this topic leave it empty
A27: Block type | B27: Block name | C27: Base Material | D27: Content planning | E27: Instructions/ notes
A28: ='Chapter Status'!C22 -> Warm-up | B28: ='Chapter Status'!D57 -> Describing a Company Basics | C28: Describing a company basics vocabulary ES_A1_describing_a_company_basics_vocabulary.mp3 Empresa de tecnología Ingeniería Datos y analítica Producto y gestión de proyectos Diseño y experiencia de usuario Marketing Control de calidad Recursos Humanos Aprendizaje y desarrollo | D28: Numbers 0-9 (in order) 30-39 70-79 Vocabulary (emphasis) Tecnología Gestión Aprendizaje Desarrollo | E28: This warm-up shouldn't be too long. Since the previous module focuses on numbers I don't think you need to add numbers here. But if you feel the need, feel free to review them. I suggest just introducing the names of the departments and empresa de tecnología.
A29: ='Chapter Status'!C23 -> Learn | B29: ='Chapter Status'!D58 -> What the Company Does | C29: ES_A1_what_the_company_does — What the company does Andes Commerce es una empresa de tecnología. La empresa crea productos digitales. Trabaja con datos, diseño y software. Ayuda a otras empresas a mejorar sus servicios en línea. ES_A1_company_departments_and_employees — Company departments and employees Andes Commerce tiene varios departamentos. El Departamento de Ingeniería tiene veinticinco empleados. El Departamento de Datos y Analítica tiene doce empleados. Producto y Gestión de Proyectos tiene ocho empleados. Diseño y Experiencia de Usuario tiene diez empleados. El equipo de Marketing tiene seis miembros. El equipo de Control de Calidad tiene cinco miembros. Hay cuatro personas en el equipo de Recursos Humanos. Hay tres personas en el departamento de Aprendizaje y Desarrollo. | D29: - Keep the focus on the noun Andes Commerce / La empresa - Reinforce third person singular - Highlight and refresh the student on the verb conjugation in third person The verbs we’ll repeatedly reinforce in third person singular are: - es (ser) - crea (crear) - trabaja (trabajar) - ayuda (ayudar) Emphasize agreement between: Singular subjects - tiene Existence structure - hay Help students distinguish between: tiene (comes from tener – to have) hay (comes from haber – there is / there are) Numbers 3–25 (reinforcement of quantity recognition) | E29: You'll need to interleave teaching new vocab and teaching structure. Suggested approach (Which should be done thorughout the tasks not in just one task: Teach "es" explain that is related to third person. relate the name of the company with their segment. teach the verb "crear", explain the conjugation "crea". You don't need to explain all the conjugations. If you want you can mention yo creo, tú creas, él/ella crea. But the focus is on the third person. Always keep in mind that teaching too much at once causes overload, and people don't actually learn when this happens. Teach La empresa (this could be before teaching the verb crear, it's a style option). Connect la empresa and what it creates. Repeate the same process to the following sentences. Teaching the verbs and relating them to the nouns. In here you want to really focus on showing HOW these verbs change because we are talking about a third person (the company). The second audio is more focused in the company departments and numbers. So, you'll want to focus on these two aspects.
A30: Practice | B30: ='Chapter Status'!D59 -> What Departments Do
A31: ='Chapter Status'!C25 -> Learn | B31: ='Chapter Status'!D60 -> Asking about a company | C31: ES_A1_sebastian_asks_elena_about_her_company — Sebastián asks Elena about her company Sebastián: ¿Dónde trabajas? Elena: Trabajo en una empresa de tecnología. Sebastián: ¿Cómo se llama la empresa? Elena: La empresa se llama Andes Commerce. Sebastián: ¿Dónde está su sede? Elena: Su sede está en Medellín, Colombia. Sebastián: ¿En qué departamento trabajas? Elena: Trabajo en el departamento de diseño y experiencia de usuario. Sebastián: ¿Cuántos empleados tiene la empresa? Elena: La empresa tiene setenta y tres empleados. Sebastián: ¿Cuál es su sitio web? Elena: Su sitio web es www.andescommerce.com Sebastián: ¿Hay empleos disponibles? Elena: ¡Creo que si! ES_A1_elena_talks_about_her_company — Elena talks about her company Hola! Trabajo en una empresa de tecnología. La empresa se llama Andes Commerce. Trabajo en el departamento de diseño y experiencia de usuario. Su sede está en Medellín, Colombia. La empresa tiene setenta y tres empleados. Su sitio web es www.andescommerce.com | D31: New question compositions to cover: ¿Dónde...? ¿Cuántos...? ¿En qué...? First person - 'Trabajo' Third person - 'La empresa' - 'Su' | E31: In the first audio you'll give them the opportunity to review questions. Most of the questions are focused on the second person, but it's ok. They need repetition, Check the previous module from the last chapter to see what words were already taught. I believe all the palabras interrogativas used in this audio were covered before. So, in theory you don't need to teach them again. But the questions are new. So you do need to teach what the questions mean. If you want you can review the palabras interrogativas function. At this level this is welcome. For the answers, there's a nice mix between conjugation of first person when Elena talks about herself, and third person when she talks about the company. make sure to create tasks that make students pay attention to this. Specially fill-in-the-blanks after multiple choice. The second audio is basically a compilation of all elena's answers. It's a good moment to wrap up any content you might want to cover. Make sure you are spreading the theory troughtout the content so it doesn't get too dense at the beginning and too repetitive at the end.
A32: ='Chapter Status'!C26 -> Practice | B32: ='Chapter Status'!D61 -> Company profile | C32: The whole audio from ES_A1_sebastian_asks_elena_about_her_company — Sebastián asks Elena about her company and ES_A1_elena_talks_about_her_company — Elena talks about her company ES_A1_andescommerce_company_profile — AndesCommerce company profile Nombre de la empresa: Andes Commerce Sector: tecnología Sede: Medellín, Colombia Número de empleados: setenta y tres Sitio web: www.andescommerce.com ES_A1_company_facts_short — Short company facts Andes Commerce es una empresa de tecnología. Su sede está en Medellín. Tiene setenta y tres empleados. Tiene ocho departamentos. ES_A1_company_details_fill_in — Company details (writing practice) La empresa se llama Andes Commerce. Es una empresa de tecnología. Su sede está en Medellín. Tiene setenta y tres empleados. Su sitio web es www.andescommerce.com. La empresa ___ AndesCommerce. __ una empresa de ________. La sede __ en Medellín. __ ________ empleados. El ____ web es www.andescommerce.com. Banco de palabras: se llama – Es – está – Tiene - setenta y tres – sitio | E32: Start the practice by using the whole audio from the previous learn block (ES_A1_sebastina_asks-elena_about_her_company) Suggested order: task with the whole audio (ask comprehension questions), then task with the whole text from the audio written and with blanks (this will allow student to see the whole conversation written and write keywords). Repeat that for the second audio (ES_A1_elena_talks_about_her_Company). Then you can proceed to other practice exercises. There are three practice base material available in the base material. The last one is a writing practice. PS: remember to include in the practice speaking tasks. This is important.
A33: ='Chapter Status'!C27 -> Review | B33: ='Chapter Status'!D62 -> Talking About a Company | C33: Grammar Highlights Glossary
A34: ='Chapter Status'!C28 -> Quiz | B34: ='Chapter Status'!D63 -> Describing a Company Quiz | C34: Module Quiz | E34: The quiz block script requires either 10 or 20 questions. To pass, learners must score at least 90%. By default, our placeholder quiz block has 10 questions, but you can change it to 20 if you prefer.
A37: Module 3 – Describing People at Work
A38: Listening Listening Objectives By the end of this module, learners will be able to recognize third-person descriptions of people (name, nationality, profession, age) in short audios. By the end of this module, learners will be able to identify corrections in short conversations using simple exchanges (e.g., “¿Es mexicana? — No, es uruguaya.”). Reading Objectives By the end of this module, learners will be able to interpret short profiles written in third person about employees in a company. By the end of this module, learners will be able to match people to their short descriptions using names, nationalities, professions, and ages. By the end of this module, learners will be able to recognize key third-person structures (se llama, es, tiene, es de) in simple workplace texts. Writing Objectives By the end of this module, learners will be able to complete short third-person descriptions of people using controlled vocabulary and guided sentence starters.
A39: Plan curricular Module 3
A40: Gramática | C40: Function | D40: Vocabulário Específico | E40: Nociones generales | F40: Nociones específicas
A41: Third-person of key verbs llamarse - se llama ser - es tener - tiene Origin and profession structures Es de… Es + nacionalidad Es + profesión Possessives (limited) su Only for contact details or names, e.g.: Su apellido es… Su correo es… We avoid plural or heavy constructions. Review only (support, not new instruction) 1st person: me llamo, soy, tengo 2nd person: te llamas, eres, tienes (they were taught in Modules 1–2) Not included yet Third-person plural (ellos/ellas) | C41: Describing a third person (name, age, nationality, job, origin). Asking for information about someone else (input only): ¿Cómo se llama? ¿De dónde es? ¿Qué edad tiene? Comparing two profiles (very simple). Giving basic information about coworkers. | D41: Focus on vocabulary previously introduced in Module 2, now used for él / ella. Personal data vocabulary reused with new focus: edad ciudad profesión correo electrónico número de teléfono New small additions: compañero/a colega persona Use professions already introduced Nationalities Countries | E41: Identidad de otra persona: nombre, apellido Origen: país, nacionalidad Edad: número + años Profesión: es + profesión | F41: 4
A42: Tácticas y estrategias pragmáticas | C42: Géneros discursivos y productos textuales | D42: Ortografía | E42: Pronunciación y prosodia | F42: Cultura, saberes y comportamientos
A43: Maintaining reference to a third person without repeating the name (pronoun use: él/ella). Subject ellipsis when describing another person: Es colombiana. (instead of Ella es colombiana.) Clarifying identity: ¿Ella? / ¿Él? (input only) | C43: Mini biographies (2–3 lines). Third-person workplace profiles (HR-style). Short descriptive dialogues between two people talking about a coworker. Character cards (profile format) (Only if I can talk to the team so we use an image). | D43: Teach explicitly: Capitalization of nationalities used as adjectives in forms. Accent marks in él (pronoun) vs el (article). Accents in: número, teléfono, país, nacionalidad, correo electrónico. Expose: Two-surname structure (briefly, through examples). | E43: Intonation of descriptive statements (flat, declarative). | F43: Talking about coworkers in a professional, respectful way (Latin American context). Workplace profiles.
A44: Block type | B44: Block name | C44: Base Material | D44: Content planning | E44: Instructions/ notes
A45: ='Chapter Status'!C65 -> Warm-up | B45: ='Chapter Status'!D65 -> Describing People at Work Basics | C45: List the words all words you want to cover during warm-up. | D45: Write your planning for this block here. Check the the Curricular plan below to check what's expected from this module. Do the same to the following rows | E45: Make sure you have audio needed on the CDN (Or that you'll record them)
A46: ='Chapter Status'!C66 -> Learn | B46: ='Chapter Status'!D66 -> Mini Biographies | C46: ES_A1_diego_mini_biography – Diego Mini Biography (Esteban narrates) Diego Ferreira es de Brasil. Es diseñador gráfico y tiene veintiséis años. Vive en Medellín, Colombia. Le gusta crear ideas visuales. Dialogue 1 — Elena asks Esteban about Diego ES_A1_elena_asks_esteban_about_diego_dialogue Elena: ¿Cómo se llama tu nuevo compañero de trabajo? Esteban: Se llama Diego Ferreira. Elena: ¿Es de Brasil? Esteban: Si, es brasileño. Elena: ¿Qué edad tiene? Esteban: Tiene veintiséis años. ES_A1_valeria_mini_biography – Valeria Mini Biography (Julieta narrates) Valeria Méndez es de República Dominicana. Es product owner y tiene treinta y cuatro años. Vive en Medellín, Colombia. Le gusta organizar productos y equipos. Dialogue 2 — Mateo asks Julieta about Valeria ES_A1_mateo_asks_julieta_about_valeria_dialogue Mateo: ¿Cómo se llama tu colega? Julieta: Se llama Valeria Méndez. Mateo: ¿Dónde vive Valeria? Julieta: Ella vive en Medellín, Colombia. Mateo: ¿Es product owner? Julieta: Sí, es product owner. Mateo: ¿Qué le gusta sobre su trabajo? Julieta: Le gusta organizar productos y equipos. ES_A1_marisol_mini_biography – Marisol Mini Biography (Basti narrates) Marisol Acevedo es de México. Es ingeniera de control de calidad y tiene cuarenta y un años. Vive en Ciudad de México. Le gusta revisar detalles y ayudar al equipo. Dialogue 3 — Camila asks Basti about Marisol ES_A1_camila_asks_basti_about_marisol_dialogue Camila: ¿Cómo se llama ella? Basti: Se llama Marisol Acevedo. Camila: ¿Es de Colombia? Basti: No, es de México. Camila: ¿Cuál es su profesión? Basti: Es ingeniera de control de calidad. | E46: When generating the scripts make sure to use the dialogue scene creator to create an effect like this one
A47: Practice | B47: ='Chapter Status'!D68 -> Asking About Mini Biographies | C47: ES_A1_noelia_mini_biography – Noelia Mini Biography (Luna Narrates) Noelia Fonseca es de Panamá. Es gerente de proyectos y tiene treinta y ocho años. Vive en Medellín, Colombia. Le gusta organizar tareas y horarios. Questions about Noelia’s Mini Biography ES_A1_questions_about_noelia_mini_biography (Julieta asks) ¿Cómo se llama? ¿De dónde es? ¿Cúal es su profesión? ¿Qué edad tiene? ¿Dónde vive? ¿Qué le gusta?
A48: Learn | B48: ='Chapter Status'!D69 -> Short Workplace Profile | C48: ES_A1_carlos_workplace_profile – Carlos Workplace Profile (Luna narrates) Carlos Andrés Vélez es ingeniero de software senior en Andes Commerce. Es colombiano y trabaja en la oficina de Medellín. Su correo es carlos.velez@andescommerce.com. Su número es 57 3.0.0 9.9.2 77.12. Su usuario es carlos-velez. Basti asks Luna about Carlos ES_A1_Basti_asks_luna_about_carlos_dialogue Basti: ¿Cómo se llama el ingeniero de software senior? Luna: Se llama Carlos Andrés Vélez. Basti: ¿Dónde trabaja? Luna: Trabaja en la oficina de Medellín. Basti: ¿Cuál es su correo electrónico? Luna: Su correo es carlos.velez@andescommerce.com ES_A1_luis_workplace_profile – Luis Workplace Profile (Angela - narrates) Luis Ignacio Torres trabaja en aprendizaje y desarrollo en Andes Commerce. Es argentino y trabaja en la oficina de Medellín. Su correo es luis.torres@andescommerce.com. Su número es +57 304 551 8890. Su usuario es luis_torres. Dialogue — Esteban asks Ángela about Luis ES_A1_esteban_asks_angela_about_luis_dialogue Esteban: ¿Donde trabaja el especialista de aprendizaje y desarrollo? Ángela: Trabaja en la oficina de Medellín. Esteban: ¿Cuál es su número de teléfono? Ángela: Su número es 57 304 551 8890. Esteban: ¿Y su usuario? Ángela: Es luis_torres
A49: Practice | B49: ='Chapter Status'!D70 -> Asking About Short Workplace Profiles | C49: ES_A1_joaquin_workplace_profile – Joaquín Workplace Profile [Mateo narrates] Joaquín Reyes es Ingeniero de Procesamiento de Lenguaje Natural en Andes Commerce. Es venezolano y trabaja en la oficina de Medellín. Su correo es joaquin.reyes@andescommerce.com. Su número es +57 3.0.5 4.4.3 29.0.1. Su usuario es joaquin-reyes. ES_A1_questions_about_joaquin_workplace_profile - Questions about Joaquin workplace profile [Esteban asks questions] ¿Cómo se llama él? ¿Cuál es su profesión? ¿De dónde es? ¿Dónde trabaja? ¿Trabaja en la oficina de Medellín? ¿Cuál es su correo electrónico? ¿Cuál es su número de teléfono? ¿Cuál es su usuario? | E49: When generating the scripts make sure to use the dialogue scene creator to create an effect like this one
A50: Review | B50: ='Chapter Status'!D71 -> Describing People at Work Review | C50: Grammar Highlights Glossary
A51: ='Chapter Status'!C72 -> Quiz | B51: ='Chapter Status'!D72 -> Describing People at Work | C51: Module Quiz | E51: The quiz block script requires either 10 or 20 questions. To pass, learners must score at least 90%. By default, our placeholder quiz block has 10 questions, but you can change it to 20 if you prefer.

Sheet Char text audio name
A2: Used in | B2: Text name | C2: Audio file name on CDN | D2: Female | E2: Male
A3: Spanish Fundamentals | B3: Alphabet | C3: ES_A1_alphabet.mp3 | D3: None | E3: None
A4: Spanish Fundamentals | B4: Alphabet practice | C4: ES_A1_alphabet_practice.mp3 | D4: None | E4: None
A5: Spanish Fundamentals | B5: First questions numbers | C5: ES_A1_first_questions_numbers
A6: Spanish Fundamentals | B6: First questions numbers Warm up | C6: ES_A1_first_questions_numbers_warmup
A7: Spanish Fundamentals | B7: Vowels aiu | C7: ES_A1_vowels_aiu
A8: Spanish Fundamentals | B8: Vowels oiu | C8: ES_A1_vowels_oiu
A9: Spanish Fundamentals | B9: Vowels uae | C9: ES_A1_vowels_uae
A10: Spanish Fundamentals | B10: Vowels | C10: ES_A1_vowels
A11: Spanish Fundamentals, Basic Personal Details | B11: Numbers 0 to 9 | C11: ES_A1_spanish_fundamentals_numbers_0_9 | D11: None | E11: None
A12: Spanish Fundamentals, Basic Personal Details | B12: The First Ten Numbers Practice | C12: ES_A1_spanish_fundamentals_numbers_mixed | D12: None
A13: Basic Personal Details | B13: Numbers 10 to 29 | C13: ES_A1_basic_personal_details_numbers_10_29 | D13: None | E13: None
A14: Basic Personal Details | B14: Numbers 10 to 29 mixed | C14: ES_A1_basic_personal_details_numbers_mixed | D14: None
A15: Basic Personal Details | B15: Personal Details in Action | C15: ES_A1_luna_personal_data_form.mp3 | D15: Luna
A16: Basic Personal Details | B16: Contact Information and Spelling | C16: ES_A1_mateo_camila_phone_number_dialogue.mp3 | D16: Camila | E16: Mateo
A17: Basic Personal Details | B17: Basic Personal Information | C17: ES_A1_mateo_email_dialogue_with_camila.mp3 | D17: Camila | E17: Mateo
A18: Basic Personal Details | B18: Basti’s Short Personal Details | C18: ES_A1_basti_personal_details | D18: None | E18: Basti
A19: Basic Personal Details | B19: Julieta’s Personal Details | C19: ES_A1_julieta_personal_details | D19: Julieta | E19: None
A20: Basic Personal Details | B20: Personal Details in Action | C20: ES_A1_personal_details_just_questions.mp3 | D20: None
A21: Basic Personal Details | B21: Esteban Personal Records dialogue with Angela | C21: ES_A1_esteban_personal_records_dialogue_with_angela.mp3 | D21: Angela | E21: Esteban
A22: Greetings and Introductions | B22: Greeting in the evening | C22: ES_A1_spanish_greetings_in_the_evening | D22: None | E22: Esteban
A23: Greetings and Introductions | B23: Greetings in the morning | C23: ES_A1_spanish_greetings_in_the_morning | D23: Elena | E23: None
A24: Greetings and Introductions | B24: Meet Camila and Mateo | C24: ES_A1_spanish_meet_camila_and_mateo | D24: Camila | E24: Mateo
A25: Greetings and Introductions | B25: Meet Luna | C25: ES_A1_spanish_meet_luna | D25: Luna | E25: None
A26: Greetings and Introductions | B26: Greeting in the afternoon | C26: ES_A1_spanish_greetings_in_the_afternoon | D26: Camila | E26: None
A27: Greetings and Introductions | B27: Greettings writing practice | C27: ES_A1_spanish_greetings_camila_practice.mp3 | D27: Camila
A28: Greetings and Introductions | B28: Introduce Yourself vocabulary | C28: ES_A1_spanish_introducing_yourself_vocabulary.mp3 | D28: None | E28: None
A29: Greetings and Introductions | B29: Meet Angela and Basti | C29: ES_A1_spanish_meet_angela_and_basti | D29: Angela | E29: Basti
A30: Greetings and Introductions | B30: Meet Julieta | C30: ES_A1_spanish_meet_julieta | D30: Julieta | E30: None
A31: Greetings and Introductions | B31: Introduce Yourself Practice | C31: ES_A1_spanish_meet_mateo_practice | D31: None | E31: None
A32: Greetings and Introductions | B32: Meet Mateo | C32: ES_A1_spanish_meet_mateo | D32: None | E32: Mateo
A33: Describing a Company and Its People | B33: Module Warm-up | C33: ES_A1_warm_up_describing_people_at_work.mp3‎ | D33: None | E33: None
A34: Describing a Company and Its People | B34: Numbers 21 to 100 | C34: ES_A1_describing_company_and_people_numbers_21_100 | D34: None | E34: None
A35: Describing a Company and Its People | B35: Numbers 75 62 63 64 91 93 96 100 40 44 47 73 71 72 79 80 | C35: ES_A1_describing_company_and_people_numbers_practice | D35: None | E35: None
A36: Describing a Company and Its People | B36: Describind a company basics vocabulary | C36: ES_A1_describing_a_company_basics_vocabulary.mp3 | D36: None
A37: Describing a Company and Its People | B37: What the Company Does | C37: ES_A1_what_the_company_does | D37: None
A38: Describing a Company and Its People | B38: Company departments and employees | C38: ES_A1_company_departments_and_employees | D38: None
A39: Describing a Company and Its People | B39: Sebastián asks Elena about her company | C39: ES_A1_sebastian_asks_elena_about_her_company | D39: Elena | E39: Basti
A40: Describing a Company and Its People | B40: Elena talks about her company | C40: ES_A1_elena_talks_about_her_company | D40: Elena | E40: None
A41: Describing a Company and Its People | B41: Short company facts | C41: ES_A1_company_facts_short | D41: None | E41: None
A42: Describing a Company and Its People | B42: Company details fill in | C42: ES_A1_company_details_fill_in | D42: None | E42: None
A43: Describing a Company and Its People | B43: Diego Mini Biography | C43: ES_A1_diego_mini_biography | D43: None | E43: Diego
A44: Describing a Company and Its People | B44: Elena asks Esteban about Diego | C44: ES_A1_elena_asks_esteban_about_diego_dialogue | D44: Elena | E44: Esteban
A45: Describing a Company and Its People | B45: Valeria Mini Biography | C45: ES_A1_valeria_mini_biography | D45: Valéria | E45: None
A46: Describing a Company and Its People | B46: Mateo asks Julieta about Valeria | C46: ES_A1_mateo_asks_julieta_about_valeria_dialogue | D46: Valéria | E46: Mateo
A47: Describing a Company and Its People | B47: Marisol Mini Biography | C47: ES_A1_marisol_mini_biography | D47: Marisol | E47: None
A48: Describing a Company and Its People | B48: Noelia Mini Biography | C48: ES_A1_noelia_mini_biography | D48: Noélia | E48: None
A49: Describing a Company and Its People | B49: Questions about Noelia’s Mini Biography | C49: ES_A1_questions_about_noelia_mini_biography | D49: Noélia | E49: None
A50: Describing a Company and Its People | B50: Basti asks Luna about Carlos | C50: ES_A1_Basti_asks_luna_about_carlos_dialogue | D50: Luna | E50: Basti
... A57: Describing a Company and Its People | B57: AndesCommerce company profile | C57: ES_A1_andescommerce_company_profile | D57: None | E57: None

Sheet Chapter template
A2: Chapter Title Objective
A3: Write the overall learning goal for the entire chapter. For example, if you are working on Block 1, state the goals you want learners to achieve by the end of Block 1.
A4: List the modules inside the chapter here
A5: Module 1 title
A6: Write the specific learning goals for the Module you are working on. A Module is a group of blocks related to the base material. When writing section objectives, make sure they follow the SMART goals framework: Specific: Focus on one clear skill or knowledge area. Measurable: Learners’ progress can be checked (e.g., quiz score, completed task). Achievable: Realistic for the learner’s level. Relevant: Directly tied to the key material in this section. Time-bound: Should be reached by the end of the section. Always start objectives with action-oriented verbs that describe observable behavior. Avoid vague words like understand or learn, since they are hard to measure. Instead, use verbs such as: Lower-level skills: identify, list, define, describe, match, recognize. Application skills: apply, demonstrate, complete, use, solve, perform. Higher-level skills: analyze, compare, create, design, evaluate. For example, for Module 1: Instead of writing a vague objective like “Students will learn greetings”, use a SMART objective: “By the end of this module, learners will be able to use three basic greetings (‘Hola,’ ‘Buenos días,’ ‘Buenas noches’) in the correct context.” You can separate the objectives by listening, reading and writing.
A7: Plan curricular Module 1
A8: Gramática | C8: Function | D8: Vocabulário Específico | E8: Nociones generales | F8: Nociones específicas
A9: List of grammar to focus on this lesson | C9: list of functions to be covered | D9: List of specific vocab | E9: List here the general field you are teaching based on the reference material | F9: List here the specific notions you are teaching based on the reference material
A10: Tácticas y estrategias pragmáticas | C10: Géneros discursivos y productos textuales | D10: Ortografía | E10: Pronunciación y prosodia | F10: Cultura, saberes y comportamientos
A11: If you are not covering this topic leave it empty | C11: If you are teaching writing you should pay extra attentio to this section. If you are not covering this topic leave it empty | D11: If you are teaching ortography list it here. If not leave it empty | E11: If you are teaching pronunciation list it here. If not leave it empty | F11: If you are not covering this topic leave it empty
A12: Block type | B12: Block name | C12: Base Material | D12: Content planning | E12: Instructions/ notes
A13: ='Chapter Status'!C16 -> Warm-up | B13: Use the formula =cellnumber from the Block on the Chapter Status tab. Do the same to the following rows | C13: List the words all words you want to cover during warm-up. | D13: Write your planning for this block here. Check the the Curricular plan below to check what's expected from this module. Do the same to the following rows | E13: Make sure you have audio needed on the CDN (Or that you'll record them)
A14: ='Chapter Status'!C17 -> Learn | C14: There can be more than one Learn block. It will depend on how long and complex is your base material. Paste the base material (dialogue or monologue) to be covered in this learning section | E14: Make sure you have audio needed on the CDN (Or that you'll record them)
A15: ='Chapter Status'!C18 -> Practice | C15: Here you'll probably use all the base material from your learn blocks and suplementer writing material, if you have any. You should mention them all here. | E15: Make sure to also include speaking tasks even if we still don't have them available.
A16: ='Chapter Status'!C19 -> Review | C16: Grammar Highlights Glossary
A17: ='Chapter Status'!C20 -> Quiz | C17: Module Quiz | E17: The quiz block script requires either 10 or 20 questions. To pass, learners must score at least 90%. By default, our placeholder quiz block has 10 questions, but you can change it to 20 if you prefer.
A21: Module 2
A23: Plan curricular Module 1
A24: Gramática | C24: Function | D24: Vocabulário Específico | E24: Nociones generales | F24: Nociones específicas
A25: List of grammar to focus on this lesson | C25: list of functions to be covered | D25: List of specific vocab | E25: List here the general field you are teaching based on the reference material | F25: List here the specific notions you are teaching based on the reference material
A26: Tácticas y estrategias pragmáticas | C26: Géneros discursivos y productos textuales | D26: Ortografía | E26: Pronunciación y prosodia | F26: Cultura, saberes y comportamientos
A27: If you are not covering this topic leave it empty | C27: If you are teaching writing you should pay extra attentio to this section. If you are not covering this topic leave it empty | D27: If you are teaching ortography list it here. If not leave it empty | E27: If you are teaching pronunciation list it here. If not leave it empty | F27: If you are not covering this topic leave it empty
A28: Block type | B28: Block name | C28: Base Material | D28: Content planning | E28: Instructions/ notes
A29: ='Chapter Status'!C22 -> Warm-up | B29: Use the formula =cellnumber from the Block on the Chapter Status tab. Do the same to the following rows | C29: List the words all words you want to cover during warm-up. | D29: Write your planning for this block here. Check the the Curricular plan below to check what's expected from this module. Do the same to the following rows | E29: Make sure you have audio needed on the CDN (Or that you'll record them)
A30: ='Chapter Status'!C23 -> Learn | C30: There can be more than one Learn block. It will depend on how long and complex is your base material. Paste the base material (dialogue or monologue) to be covered in this learning section | E30: Make sure you have audio needed on the CDN (Or that you'll record them)
A31: ='Chapter Status'!C26 -> Practice | C31: Here you'll probably use all the base material from your learn blocks and suplementer writing material, if you have any. You should mention them all here. | E31: Make sure to also include speaking tasks even if we still don't have them available.
A32: ='Chapter Status'!C27 -> Review | C32: Grammar Highlights Glossary
A33: ='Chapter Status'!C28 -> Quiz | C33: Module Quiz | E33: The quiz block script requires either 10 or 20 questions. To pass, learners must score at least 90%. By default, our placeholder quiz block has 10 questions, but you can change it to 20 if you prefer.
A36: Module 3 – First Questions
A38: Plan curricular Module 1
A39: Gramática | C39: Function | D39: Vocabulário Específico | E39: Nociones generales | F39: Nociones específicas
A40: List of grammar to focus on this lesson | C40: list of functions to be covered | D40: List of specific vocab | E40: List here the general field you are teaching based on the reference material | F40: List here the specific notions you are teaching based on the reference material
A41: Tácticas y estrategias pragmáticas | C41: Géneros discursivos y productos textuales | D41: Ortografía | E41: Pronunciación y prosodia | F41: Cultura, saberes y comportamientos
A42: If you are not covering this topic leave it empty | C42: If you are teaching writing you should pay extra attentio to this section. If you are not covering this topic leave it empty | D42: If you are teaching ortography list it here. If not leave it empty | E42: If you are teaching pronunciation list it here. If not leave it empty | F42: If you are not covering this topic leave it empty
A43: Block type | B43: Block name | C43: Base Material | D43: Content planning | E43: Instructions/ notes
A44: ='Chapter Status'!C30 -> Warm-up | B44: Use the formula =cellnumber from the Block on the Chapter Status tab. Do the same to the following rows | C44: List the words all words you want to cover during warm-up. | D44: Write your planning for this block here. Check the the Curricular plan below to check what's expected from this module. Do the same to the following rows | E44: Make sure you have audio needed on the CDN (Or that you'll record them)
A45: ='Chapter Status'!C31 -> Learn | C45: There can be more than one Learn block. It will depend on how long and complex is your base material. Paste the base material (dialogue or monologue) to be covered in this learning section | E45: Make sure you have audio needed on the CDN (Or that you'll record them)
A46: ='Chapter Status'!C32 -> Practice | C46: Here you'll probably use all the base material from your learn blocks and suplementer writing material, if you have any. You should mention them all here. | E46: Make sure to also include speaking tasks even if we still don't have them available.
A47: ='Chapter Status'!C33 -> Review | C47: Grammar Highlights Glossary
A48: ='Chapter Status'!C34 -> Quiz | C48: Module Quiz | E48: The quiz block script requires either 10 or 20 questions. To pass, learners must score at least 90%. By default, our placeholder quiz block has 10 questions, but you can change it to 20 if you prefer.

Sheet Character Height
A1: Character name | B1: Height | D1: Coordinates
A2: Ángela | B2: Short | E2: Female | F2: Male
A3: Camila | B3: Tall | D3: Tall | E3: y: 12 z: 1.5 | F3: y: 12 z: 1.5
A4: Elena | B4: Short | D4: Short | E4: y: 25 z: 1.5 | F4: y: 25 z: 1.5
A5: Julieta | B5: Tall
A6: Luna | B6: Short | D6: Dialog scenes | E6: y: 17 z: 1.5
A7: Esteban | B7: Short
A8: Mateo | B8: Tall
A9: Sebastián | B9: Short
A11: Marisol | B11: Tall
A12: Noelia | B12: Short
A13: Valeria | B13: Tall
A14: Carlos | B14: Tall
A15: Diego | B15: Tall
A16: Joaquín | B16: Tall
A17: Luis | B17: Short
A18: René | B18: Short (?)

Sheet Helper-dropdown
A1: =IFERROR(__xludf.DUMMYFUNCTION("FILTER(Chapter_Status[Name], Chapter_Status[Type] = ""Chapter"")"),"Welcome to A1 Professional Spanish ") -> Welcome to A1 Professional Spanish
A2: =IFERROR(__xludf.DUMMYFUNCTION("""COMPUTED_VALUE"""),"Spanish Fundamentals") -> Spanish Fundamentals
A3: =IFERROR(__xludf.DUMMYFUNCTION("""COMPUTED_VALUE"""),"Greetings and Introductions") -> Greetings and Introductions
A4: =IFERROR(__xludf.DUMMYFUNCTION("""COMPUTED_VALUE"""),"Basic Personal Details") -> Basic Personal Details
A5: =IFERROR(__xludf.DUMMYFUNCTION("""COMPUTED_VALUE"""),"Describing a Company and Its People") -> Describing a Company and Its People

Sheet template
A1: Block 1 Introductions & Basic Communication
A2: Block's Objective
A3: Write the overall learning goal for the entire block. For example, if you are working on Block 1, state the goals you want learners to achieve by the end of Block 1.
A4: List the lessons inside the block here
A6: Lesson number - lesson name
A7: Write the specific learning goals for the section you are working on. A section is a group of tasks related to the same key material (base text). For example, if you are designing tasks for Block 1, Dialogue 1, write the objectives specific to Dialogue 1 here. When writing section objectives, make sure they follow the SMART goals framework: Specific: Focus on one clear skill or knowledge area. Measurable: Learners’ progress can be checked (e.g., quiz score, completed task). Achievable: Realistic for the learner’s level. Relevant: Directly tied to the key material in this section. Time-bound: Should be reached by the end of the section. Always start objectives with action-oriented verbs that describe observable behavior. Avoid vague words like understand or learn, since they are hard to measure. Instead, use verbs such as: Lower-level skills: identify, list, define, describe, match, recognize. Application skills: apply, demonstrate, complete, use, solve, perform. Higher-level skills: analyze, compare, create, design, evaluate. For example, for Block 1, Dialogue 1: Instead of writing a vague objective like “Students will learn greetings”, use a SMART objective: “By the end of this section, learners will be able to use three basic greetings (‘Hola,’ ‘Buenos días,’ ‘Buenas noches’) in the correct context.”
A8: Content
A9: Key words/sentences | D9: Texts | G9: Support material
A10: Paste the keywords / sentencess you will be using for the entire section, or include a link to it. Using the example above, here you would paste key words to preceed dialogue 1 of Block 1. | D10: Paste the text you will be using for the entire section, or include a link to it. Using the example above, here you would paste Dialogue 1 of Block 1. | G10: If you'll use extra audios, images, or reading practices, list them here so you can prepare them before designing the lessons. For example, if this section requires a review text, paste it here or provide a link to it.
A11: Plan curricular
A12: Gramática | B12: Function | D12: Vocabulário Específico | F12: Nociones generales | H12: Nociones específicas
A13: List of grammar to focus on this lesson | B13: list of functions to be covered | D13: List of specific vocab | F13: List here the general field you are teaching based on the reference material | H13: List here the specific notions you are teaching based on the reference material
A14: Tácticas y estrategias pragmáticas | B14: Géneros discursivos y productos textuales | D14: Ortografía | F14: Pronunciación y prosodia | H14: Cultura, saberes y comportamientos
A15: If you are not covering this topic leave it empty | B15: If you are teaching writing you should pay extra attentio to this section. If you are not covering this topic leave it empty | D15: If you are teaching ortography list it here. If not leave it empty | F15: If you are teaching pronunciation list it here. If not leave it empty | H15: If you are not covering this topic leave it empty
A16: Lesson Structure
A17: Lessons stage | B17: FALSE | C17: Reading | D17: FALSE | E17: Writing | F17: FALSE | G17: Listening | H17: FALSE | I17: Speaking
A18: Introduction | B18: Are you going to provide an introductory practice? if so, write a short plan here. This section is supposed to guide you when desiging the tasks
A19: Learning Activities | B19: List the tasks types you are planning to use when students are learning the content.
A20: Guided Practice | B20: Guided practice includes tasks where learners work with clear instructions, prompts, or scaffolds that direct their thinking step by step. The goal is to ensure they see how the concept works with support.
A21: Independent Practice | B21: Independent practice includes tasks where learners apply what they learned on their own, with little or no guidance. The goal is for them to demonstrate mastery independently.
A22: Review & Wrap-Up | B22: If you section contains a review or wrap-up. describe it here
A23: Assessment
A24: Lessons stage | B24: FALSE | C24: Reading | D24: FALSE | E24: Writing | F24: FALSE | G24: Listening | H24: FALSE | I24: Speaking
A25: Assessment | B25: Does your section contain assessments? If so, which skill will it use? how are you going to assess their success?
A26: Feedback Style | B26: Does it include performance feedback if so, how?
A27: Passing criteria | B27: What should they do to pass?
A28: Notes / Suport material
A29: If you want to add additional Observations / Optional Resources that's the place to plan it.

Sheet Sheet5
B2: # Nivel A1
B4: ###### 1.1.1. Nombres propios
B5: - [v. Ortografía 1.4.3.]
B6: - Antropónimos
B7: - Nombres de pila sin artículo
B8: - Examples/Notes:
B9: - María, Antonio
B10: - Hipocorísticos y diminutivos
B11: - Examples/Notes:
B12: - Pepe (José), Paco (Francisco), Chelo (Consuelo), Lola (Dolores)
B13: - [Hispanoamérica] Chayo (Rosario), Chava (Isabel), Güicho (Luis), Pancho (Francisco)
B14: - Apellidos sin artículo
... B3868: - hablar, escribir
